{
"meta":{"test_sets":[],"test_metrics":[],"learn_metrics":[{"best_value":"Min","name":"RMSE"}],"launch_mode":"Train","parameters":"","iteration_count":1000,"learn_sets":["learn"],"name":"experiment"},
"iterations":[
{"learn":[14.59871775],"iteration":0,"passed_time":0.1492879608,"remaining_time":149.1386729},
{"learn":[14.22518863],"iteration":1,"passed_time":0.151426479,"remaining_time":75.56181301},
{"learn":[13.8866124],"iteration":2,"passed_time":0.1534964154,"remaining_time":51.01197539},
{"learn":[13.52356875],"iteration":3,"passed_time":0.1553112706,"remaining_time":38.67250638},
{"learn":[13.18870211],"iteration":4,"passed_time":0.1588455771,"remaining_time":31.61026985},
{"learn":[12.9124226],"iteration":5,"passed_time":0.1609900653,"remaining_time":26.67068749},
{"learn":[12.60003351],"iteration":6,"passed_time":0.1632920175,"remaining_time":23.16413906},
{"learn":[12.32990573],"iteration":7,"passed_time":0.1651049981,"remaining_time":20.47301976},
{"learn":[12.0660619],"iteration":8,"passed_time":0.166795174,"remaining_time":18.36600194},
{"learn":[11.77309809],"iteration":9,"passed_time":0.1686313551,"remaining_time":16.69450415},
{"learn":[11.49227636],"iteration":10,"passed_time":0.1707212306,"remaining_time":15.34939065},
{"learn":[11.26264833],"iteration":11,"passed_time":0.173434847,"remaining_time":14.27946907},
{"learn":[11.04260393],"iteration":12,"passed_time":0.175840298,"remaining_time":13.35033647},
{"learn":[10.79916926],"iteration":13,"passed_time":0.1775672298,"remaining_time":12.50580633},
{"learn":[10.5541002],"iteration":14,"passed_time":0.1790479576,"remaining_time":11.75748255},
{"learn":[10.31918115],"iteration":15,"passed_time":0.1806294917,"remaining_time":11.10871374},
{"learn":[10.10004441],"iteration":16,"passed_time":0.1821131574,"remaining_time":10.53042551},
{"learn":[9.894556723],"iteration":17,"passed_time":0.1836204827,"remaining_time":10.01751744},
{"learn":[9.690174082],"iteration":18,"passed_time":0.186400465,"remaining_time":9.624150323},
{"learn":[9.506034866],"iteration":19,"passed_time":0.1883591112,"remaining_time":9.229596446},
{"learn":[9.338524633],"iteration":20,"passed_time":0.190050629,"remaining_time":8.859979325},
{"learn":[9.170203312],"iteration":21,"passed_time":0.1914141546,"remaining_time":8.509229237},
{"learn":[9.010299969],"iteration":22,"passed_time":0.1928700756,"remaining_time":8.192785384},
{"learn":[8.843866678],"iteration":23,"passed_time":0.1941018665,"remaining_time":7.893475905},
{"learn":[8.690548059],"iteration":24,"passed_time":0.1952488271,"remaining_time":7.614704255},
{"learn":[8.555307687],"iteration":25,"passed_time":0.1963528972,"remaining_time":7.355681612},
{"learn":[8.413851302],"iteration":26,"passed_time":0.197471143,"remaining_time":7.116274895},
{"learn":[8.29256019],"iteration":27,"passed_time":0.1987150101,"remaining_time":6.898249635},
{"learn":[8.162193833],"iteration":28,"passed_time":0.2006473521,"remaining_time":6.718226858},
{"learn":[8.040736294],"iteration":29,"passed_time":0.2022863425,"remaining_time":6.540591742},
{"learn":[7.921220278],"iteration":30,"passed_time":0.2035481234,"remaining_time":6.362520373},
{"learn":[7.809589039],"iteration":31,"passed_time":0.2045088968,"remaining_time":6.186394127},
{"learn":[7.699675801],"iteration":32,"passed_time":0.2055188607,"remaining_time":6.022325403},
{"learn":[7.60645267],"iteration":33,"passed_time":0.2062941433,"remaining_time":5.861180659},
{"learn":[7.498880302],"iteration":34,"passed_time":0.2069917498,"remaining_time":5.707058244},
{"learn":[7.401158744],"iteration":35,"passed_time":0.2077014909,"remaining_time":5.561784367},
{"learn":[7.306431077],"iteration":36,"passed_time":0.208368667,"remaining_time":5.423216929},
{"learn":[7.223863468],"iteration":37,"passed_time":0.2090206772,"remaining_time":5.291523459},
{"learn":[7.143477682],"iteration":38,"passed_time":0.2096717223,"remaining_time":5.166526285},
{"learn":[7.062817131],"iteration":39,"passed_time":0.2104067169,"remaining_time":5.049761206},
{"learn":[6.990793435],"iteration":40,"passed_time":0.2113330752,"remaining_time":4.943132172},
{"learn":[6.931862224],"iteration":41,"passed_time":0.2122682802,"remaining_time":4.841738391},
{"learn":[6.858296558],"iteration":42,"passed_time":0.213336506,"remaining_time":4.747977588},
{"learn":[6.786268161],"iteration":43,"passed_time":0.2143710362,"remaining_time":4.657697968},
{"learn":[6.717118549],"iteration":44,"passed_time":0.2152782031,"remaining_time":4.568681866},
{"learn":[6.652948106],"iteration":45,"passed_time":0.2161587695,"remaining_time":4.482944916},
{"learn":[6.589686076],"iteration":46,"passed_time":0.216922629,"remaining_time":4.398452455},
{"learn":[6.531283097],"iteration":47,"passed_time":0.2176345922,"remaining_time":4.316419411},
{"learn":[6.471368031],"iteration":48,"passed_time":0.2183184408,"remaining_time":4.237159942},
{"learn":[6.416481395],"iteration":49,"passed_time":0.2189319667,"remaining_time":4.159707368},
{"learn":[6.369870822],"iteration":50,"passed_time":0.2195345237,"remaining_time":4.08506398},
{"learn":[6.325678067],"iteration":51,"passed_time":0.22011006,"remaining_time":4.012775709},
{"learn":[6.275766122],"iteration":52,"passed_time":0.2207195741,"remaining_time":3.943800692},
{"learn":[6.224773967],"iteration":53,"passed_time":0.2212939923,"remaining_time":3.876742903},
{"learn":[6.182249254],"iteration":54,"passed_time":0.2219124752,"remaining_time":3.812859801},
{"learn":[6.139904173],"iteration":55,"passed_time":0.2225019666,"remaining_time":3.750747437},
{"learn":[6.100525536],"iteration":56,"passed_time":0.223090257,"remaining_time":3.690773901},
{"learn":[6.062568564],"iteration":57,"passed_time":0.2237983133,"remaining_time":3.634793295},
{"learn":[6.030559288],"iteration":58,"passed_time":0.224405402,"remaining_time":3.579075989},
{"learn":[5.997931376],"iteration":59,"passed_time":0.225013262,"remaining_time":3.525207772},
{"learn":[5.964103835],"iteration":60,"passed_time":0.2256343714,"remaining_time":3.473289749},
{"learn":[5.933729724],"iteration":61,"passed_time":0.2263192953,"remaining_time":3.423991919},
{"learn":[5.901932711],"iteration":62,"passed_time":0.2269768624,"remaining_time":3.375830478},
{"learn":[5.873727795],"iteration":63,"passed_time":0.2278521692,"remaining_time":3.332337975},
{"learn":[5.846485734],"iteration":64,"passed_time":0.2292816186,"remaining_time":3.298127898},
{"learn":[5.820630862],"iteration":65,"passed_time":0.2302048892,"remaining_time":3.257747978},
{"learn":[5.793646238],"iteration":66,"passed_time":0.2314685885,"remaining_time":3.223286463},
{"learn":[5.765388646],"iteration":67,"passed_time":0.2322207554,"remaining_time":3.182790354},
{"learn":[5.747073912],"iteration":68,"passed_time":0.2328944831,"remaining_time":3.14238788},
{"learn":[5.722315217],"iteration":69,"passed_time":0.2335288858,"remaining_time":3.102598054},
{"learn":[5.699970599],"iteration":70,"passed_time":0.2341887286,"remaining_time":3.064244068},
{"learn":[5.682732647],"iteration":71,"passed_time":0.234847885,"remaining_time":3.026928296},
{"learn":[5.663525791],"iteration":72,"passed_time":0.235534065,"remaining_time":2.990959976},
{"learn":[5.642381613],"iteration":73,"passed_time":0.2362554992,"remaining_time":2.956386382},
{"learn":[5.621404779],"iteration":74,"passed_time":0.2370037763,"remaining_time":2.923046574},
{"learn":[5.602460129],"iteration":75,"passed_time":0.2376977639,"remaining_time":2.889904392},
{"learn":[5.587337574],"iteration":76,"passed_time":0.2383423784,"remaining_time":2.857013186},
{"learn":[5.572393026],"iteration":77,"passed_time":0.2389891289,"remaining_time":2.824974063},
{"learn":[5.558425806],"iteration":78,"passed_time":0.2396565591,"remaining_time":2.793970771},
{"learn":[5.541518902],"iteration":79,"passed_time":0.2403007326,"remaining_time":2.763458425},
{"learn":[5.526157283],"iteration":80,"passed_time":0.2409679846,"remaining_time":2.733945406},
{"learn":[5.511746977],"iteration":81,"passed_time":0.2416730007,"remaining_time":2.705558715},
{"learn":[5.504975022],"iteration":82,"passed_time":0.2420153103,"remaining_time":2.673831802},
{"learn":[5.493980522],"iteration":83,"passed_time":0.2430526935,"remaining_time":2.650431753},
{"learn":[5.480745463],"iteration":84,"passed_time":0.2446384554,"remaining_time":2.63346102},
{"learn":[5.464052013],"iteration":85,"passed_time":0.2459509673,"remaining_time":2.613944001},
{"learn":[5.449143727],"iteration":86,"passed_time":0.2472851946,"remaining_time":2.595073364},
{"learn":[5.438255432],"iteration":87,"passed_time":0.2481327547,"remaining_time":2.571557639},
{"learn":[5.425927931],"iteration":88,"passed_time":0.2490076718,"remaining_time":2.548831337},
{"learn":[5.412331217],"iteration":89,"passed_time":0.2496915104,"remaining_time":2.524658605},
{"learn":[5.400691499],"iteration":90,"passed_time":0.2503554005,"remaining_time":2.500802846},
{"learn":[5.391618744],"iteration":91,"passed_time":0.2510181711,"remaining_time":2.477440211},
{"learn":[5.380766572],"iteration":92,"passed_time":0.2516556307,"remaining_time":2.454318893},
{"learn":[5.372207183],"iteration":93,"passed_time":0.2523116087,"remaining_time":2.431854441},
{"learn":[5.362918837],"iteration":94,"passed_time":0.2529549929,"remaining_time":2.409729143},
{"learn":[5.348292324],"iteration":95,"passed_time":0.2536796728,"remaining_time":2.388816918},
{"learn":[5.339772295],"iteration":96,"passed_time":0.2544803095,"remaining_time":2.369028036},
{"learn":[5.331515983],"iteration":97,"passed_time":0.2553824153,"remaining_time":2.350560598},
{"learn":[5.323861644],"iteration":98,"passed_time":0.2560333114,"remaining_time":2.330161753},
{"learn":[5.313277281],"iteration":99,"passed_time":0.2567202783,"remaining_time":2.310482505},
{"learn":[5.30685627],"iteration":100,"passed_time":0.2575041547,"remaining_time":2.292041932},
{"learn":[5.29652059],"iteration":101,"passed_time":0.2582956687,"remaining_time":2.274014809},
{"learn":[5.288350766],"iteration":102,"passed_time":0.2594427208,"remaining_time":2.259418646},
{"learn":[5.27993346],"iteration":103,"passed_time":0.2607556597,"remaining_time":2.246510299},
{"learn":[5.271789139],"iteration":104,"passed_time":0.262785613,"remaining_time":2.23993451},
{"learn":[5.262684686],"iteration":105,"passed_time":0.2636904769,"remaining_time":2.223955531},
{"learn":[5.251619772],"iteration":106,"passed_time":0.2644985169,"remaining_time":2.207450239},
{"learn":[5.241012171],"iteration":107,"passed_time":0.2652361427,"remaining_time":2.190654067},
{"learn":[5.232684032],"iteration":108,"passed_time":0.2660549325,"remaining_time":2.174816008},
{"learn":[5.224267141],"iteration":109,"passed_time":0.2677474284,"remaining_time":2.166320103},
{"learn":[5.216324968],"iteration":110,"passed_time":0.2689393581,"remaining_time":2.153937742},
{"learn":[5.211102527],"iteration":111,"passed_time":0.2697567542,"remaining_time":2.138785694},
{"learn":[5.206364257],"iteration":112,"passed_time":0.2706490842,"remaining_time":2.124475555},
{"learn":[5.196937641],"iteration":113,"passed_time":0.2714862249,"remaining_time":2.109971889},
{"learn":[5.190746047],"iteration":114,"passed_time":0.2723829304,"remaining_time":2.096164291},
{"learn":[5.181885213],"iteration":115,"passed_time":0.2753983025,"remaining_time":2.098724995},
{"learn":[5.178293568],"iteration":116,"passed_time":0.2766590915,"remaining_time":2.087948528},
{"learn":[5.170991438],"iteration":117,"passed_time":0.2786207107,"remaining_time":2.082571753},
{"learn":[5.166257212],"iteration":118,"passed_time":0.2799205062,"remaining_time":2.072352655},
{"learn":[5.161421246],"iteration":119,"passed_time":0.2817242935,"remaining_time":2.065978152},
{"learn":[5.158223542],"iteration":120,"passed_time":0.2826026397,"remaining_time":2.052956366},
{"learn":[5.15470988],"iteration":121,"passed_time":0.2832971489,"remaining_time":2.038810629},
{"learn":[5.146388143],"iteration":122,"passed_time":0.2840887046,"remaining_time":2.025575561},
{"learn":[5.139529364],"iteration":123,"passed_time":0.2849022883,"remaining_time":2.012696811},
{"learn":[5.134276023],"iteration":124,"passed_time":0.2856649625,"remaining_time":1.999654737},
{"learn":[5.128536065],"iteration":125,"passed_time":0.2879935209,"remaining_time":1.997669343},
{"learn":[5.123300353],"iteration":126,"passed_time":0.2894993879,"remaining_time":1.990023352},
{"learn":[5.116200518],"iteration":127,"passed_time":0.2911592899,"remaining_time":1.983522663},
{"learn":[5.108728704],"iteration":128,"passed_time":0.2937208626,"remaining_time":1.983185049},
{"learn":[5.104075866],"iteration":129,"passed_time":0.294663088,"remaining_time":1.97197605},
{"learn":[5.100317606],"iteration":130,"passed_time":0.2956294113,"remaining_time":1.961083652},
{"learn":[5.095814182],"iteration":131,"passed_time":0.2964269648,"remaining_time":1.94923186},
{"learn":[5.092146915],"iteration":132,"passed_time":0.2971444837,"remaining_time":1.937024567},
{"learn":[5.085258329],"iteration":133,"passed_time":0.2982674471,"remaining_time":1.927609024},
{"learn":[5.079219421],"iteration":134,"passed_time":0.2993046195,"remaining_time":1.917766636},
{"learn":[5.076476829],"iteration":135,"passed_time":0.3000803114,"remaining_time":1.906392567},
{"learn":[5.072133867],"iteration":136,"passed_time":0.3007367518,"remaining_time":1.89442202},
{"learn":[5.067031564],"iteration":137,"passed_time":0.3014015956,"remaining_time":1.882667937},
{"learn":[5.061358312],"iteration":138,"passed_time":0.3020418561,"remaining_time":1.870921137},
{"learn":[5.056759124],"iteration":139,"passed_time":0.3032911114,"remaining_time":1.86307397},
{"learn":[5.050254],"iteration":140,"passed_time":0.3054754508,"remaining_time":1.861017108},
{"learn":[5.048376474],"iteration":141,"passed_time":0.3078880447,"remaining_time":1.860337622},
{"learn":[5.042603751],"iteration":142,"passed_time":0.3096843448,"remaining_time":1.855940444},
{"learn":[5.037477349],"iteration":143,"passed_time":0.3113387485,"remaining_time":1.850735894},
{"learn":[5.03230489],"iteration":144,"passed_time":0.3122803196,"remaining_time":1.841377057},
{"learn":[5.025976187],"iteration":145,"passed_time":0.3130996333,"remaining_time":1.831418403},
{"learn":[5.01952451],"iteration":146,"passed_time":0.3141416743,"remaining_time":1.822876518},
{"learn":[5.017569424],"iteration":147,"passed_time":0.3150410511,"remaining_time":1.813614699},
{"learn":[5.008962367],"iteration":148,"passed_time":0.3157877957,"remaining_time":1.803593383},
{"learn":[5.003880266],"iteration":149,"passed_time":0.317386014,"remaining_time":1.798520746},
{"learn":[4.996387564],"iteration":150,"passed_time":0.3194213074,"remaining_time":1.795951589},
{"learn":[4.993361683],"iteration":151,"passed_time":0.3233232817,"remaining_time":1.803803571},
{"learn":[4.99005752],"iteration":152,"passed_time":0.3258541591,"remaining_time":1.803911586},
{"learn":[4.986908764],"iteration":153,"passed_time":0.326789207,"remaining_time":1.795218631},
{"learn":[4.985207175],"iteration":154,"passed_time":0.3276078816,"remaining_time":1.785991354},
{"learn":[4.979003494],"iteration":155,"passed_time":0.3284708392,"remaining_time":1.777111464},
{"learn":[4.973142217],"iteration":156,"passed_time":0.330301225,"remaining_time":1.773528234},
{"learn":[4.967056696],"iteration":157,"passed_time":0.3311900491,"remaining_time":1.764949502},
{"learn":[4.961460696],"iteration":158,"passed_time":0.3357995159,"remaining_time":1.776147125},
{"learn":[4.954240363],"iteration":159,"passed_time":0.3391010134,"remaining_time":1.78028032},
{"learn":[4.952320707],"iteration":160,"passed_time":0.3397862391,"remaining_time":1.770687295},
{"learn":[4.948337777],"iteration":161,"passed_time":0.3409125287,"remaining_time":1.763485796},
{"learn":[4.943228639],"iteration":162,"passed_time":0.341798883,"remaining_time":1.755126779},
{"learn":[4.938545759],"iteration":163,"passed_time":0.3427925909,"remaining_time":1.747406134},
{"learn":[4.935330572],"iteration":164,"passed_time":0.3442458265,"remaining_time":1.742092516},
{"learn":[4.932051543],"iteration":165,"passed_time":0.3450060193,"remaining_time":1.733343494},
{"learn":[4.928964153],"iteration":166,"passed_time":0.3456459663,"remaining_time":1.724090359},
{"learn":[4.922860227],"iteration":167,"passed_time":0.3466543982,"remaining_time":1.716764639},
{"learn":[4.917668772],"iteration":168,"passed_time":0.3490543786,"remaining_time":1.716356146},
{"learn":[4.910365386],"iteration":169,"passed_time":0.3521719913,"remaining_time":1.719427958},
{"learn":[4.906457206],"iteration":170,"passed_time":0.353476177,"remaining_time":1.713635969},
{"learn":[4.901996508],"iteration":171,"passed_time":0.3544814016,"remaining_time":1.70645698},
{"learn":[4.896816173],"iteration":172,"passed_time":0.355411889,"remaining_time":1.698992094},
{"learn":[4.891123132],"iteration":173,"passed_time":0.3562299149,"remaining_time":1.691068447},
{"learn":[4.887630202],"iteration":174,"passed_time":0.3571795402,"remaining_time":1.683846404},
{"learn":[4.885259712],"iteration":175,"passed_time":0.3586448028,"remaining_time":1.679109759},
{"learn":[4.880659728],"iteration":176,"passed_time":0.359552765,"remaining_time":1.671818789},
{"learn":[4.877299723],"iteration":177,"passed_time":0.3604143984,"remaining_time":1.664385593},
{"learn":[4.874038772],"iteration":178,"passed_time":0.3649024928,"remaining_time":1.67365892},
{"learn":[4.86943698],"iteration":179,"passed_time":0.3686251866,"remaining_time":1.679292517},
{"learn":[4.861268711],"iteration":180,"passed_time":0.3701056407,"remaining_time":1.674676905},
{"learn":[4.858673056],"iteration":181,"passed_time":0.3712829317,"remaining_time":1.668733176},
{"learn":[4.854036207],"iteration":182,"passed_time":0.3731085858,"remaining_time":1.665736145},
{"learn":[4.85130244],"iteration":183,"passed_time":0.3740130788,"remaining_time":1.658666697},
{"learn":[4.847510084],"iteration":184,"passed_time":0.3752094611,"remaining_time":1.652949788},
{"learn":[4.845691673],"iteration":185,"passed_time":0.3773555178,"remaining_time":1.651437589},
{"learn":[4.842058646],"iteration":186,"passed_time":0.380444264,"remaining_time":1.654017041},
{"learn":[4.838623675],"iteration":187,"passed_time":0.3816098538,"remaining_time":1.648229794},
{"learn":[4.834602161],"iteration":188,"passed_time":0.3827219411,"remaining_time":1.642261874},
{"learn":[4.830858976],"iteration":189,"passed_time":0.3836321255,"remaining_time":1.635484324},
{"learn":[4.827590511],"iteration":190,"passed_time":0.3845200881,"remaining_time":1.62867409},
{"learn":[4.822246226],"iteration":191,"passed_time":0.3855402194,"remaining_time":1.622481757},
{"learn":[4.816686395],"iteration":192,"passed_time":0.3863959008,"remaining_time":1.615655399},
{"learn":[4.814797121],"iteration":193,"passed_time":0.387335895,"remaining_time":1.609240883},
{"learn":[4.811639392],"iteration":194,"passed_time":0.3882891846,"remaining_time":1.602937403},
{"learn":[4.804813432],"iteration":195,"passed_time":0.3929852559,"remaining_time":1.61204156},
{"learn":[4.80251613],"iteration":196,"passed_time":0.3953051927,"remaining_time":1.611320151},
{"learn":[4.800087884],"iteration":197,"passed_time":0.3966873402,"remaining_time":1.606784075},
{"learn":[4.794773135],"iteration":198,"passed_time":0.3976707905,"remaining_time":1.60067489},
{"learn":[4.791664833],"iteration":199,"passed_time":0.3984522777,"remaining_time":1.593809111},
{"learn":[4.785989873],"iteration":200,"passed_time":0.399221627,"remaining_time":1.586955622},
{"learn":[4.782387142],"iteration":201,"passed_time":0.4000005295,"remaining_time":1.580200112},
{"learn":[4.778623704],"iteration":202,"passed_time":0.4008219692,"remaining_time":1.57367049},
{"learn":[4.775772178],"iteration":203,"passed_time":0.401720443,"remaining_time":1.567497415},
{"learn":[4.77023101],"iteration":204,"passed_time":0.4025312425,"remaining_time":1.561035794},
{"learn":[4.764496689],"iteration":205,"passed_time":0.4032786103,"remaining_time":1.554384546},
{"learn":[4.763138716],"iteration":206,"passed_time":0.4041719428,"remaining_time":1.54834952},
{"learn":[4.758053283],"iteration":207,"passed_time":0.4099078469,"remaining_time":1.560802956},
{"learn":[4.755063788],"iteration":208,"passed_time":0.4110509948,"remaining_time":1.555700176},
{"learn":[4.752465267],"iteration":209,"passed_time":0.411822059,"remaining_time":1.549235365},
{"learn":[4.748067377],"iteration":210,"passed_time":0.4124835023,"remaining_time":1.542414613},
{"learn":[4.744163298],"iteration":211,"passed_time":0.4131296774,"remaining_time":1.535595216},
{"learn":[4.736670896],"iteration":212,"passed_time":0.4137897548,"remaining_time":1.52888515},
{"learn":[4.73349255],"iteration":213,"passed_time":0.4144248232,"remaining_time":1.522139771},
{"learn":[4.731864595],"iteration":214,"passed_time":0.415029218,"remaining_time":1.515339238},
{"learn":[4.728398311],"iteration":215,"passed_time":0.4156647341,"remaining_time":1.508709035},
{"learn":[4.723865975],"iteration":216,"passed_time":0.4162934455,"remaining_time":1.502109529},
{"learn":[4.723483365],"iteration":217,"passed_time":0.4168829336,"remaining_time":1.495424101},
{"learn":[4.72095416],"iteration":218,"passed_time":0.41749775,"remaining_time":1.48888467},
{"learn":[4.716173382],"iteration":219,"passed_time":0.4181403122,"remaining_time":1.482497471},
{"learn":[4.710563974],"iteration":220,"passed_time":0.418932427,"remaining_time":1.476689415},
{"learn":[4.707160263],"iteration":221,"passed_time":0.4195849891,"remaining_time":1.470437484},
{"learn":[4.70408351],"iteration":222,"passed_time":0.4206307022,"remaining_time":1.46560563},
{"learn":[4.702501831],"iteration":223,"passed_time":0.4217927272,"remaining_time":1.461210519},
{"learn":[4.700269738],"iteration":224,"passed_time":0.4227863752,"remaining_time":1.456264181},
{"learn":[4.695346302],"iteration":225,"passed_time":0.4242367515,"remaining_time":1.452917016},
{"learn":[4.689769299],"iteration":226,"passed_time":0.4252620449,"remaining_time":1.448139034},
{"learn":[4.687919514],"iteration":227,"passed_time":0.4265411077,"remaining_time":1.444253224},
{"learn":[4.682982074],"iteration":228,"passed_time":0.4272829806,"remaining_time":1.438581564},
{"learn":[4.679578702],"iteration":229,"passed_time":0.4279503539,"remaining_time":1.432703359},
{"learn":[4.675751423],"iteration":230,"passed_time":0.4285951496,"remaining_time":1.426795109},
{"learn":[4.672710726],"iteration":231,"passed_time":0.4292294201,"remaining_time":1.420897391},
{"learn":[4.6690533],"iteration":232,"passed_time":0.4299564785,"remaining_time":1.415350296},
{"learn":[4.667595702],"iteration":233,"passed_time":0.430635163,"remaining_time":1.409686046},
{"learn":[4.664241291],"iteration":234,"passed_time":0.4312859989,"remaining_time":1.403973571},
{"learn":[4.662246999],"iteration":235,"passed_time":0.4319382537,"remaining_time":1.398308584},
{"learn":[4.658668443],"iteration":236,"passed_time":0.4325918945,"remaining_time":1.392690361},
{"learn":[4.658017572],"iteration":237,"passed_time":0.4334304918,"remaining_time":1.387706028},
{"learn":[4.657656705],"iteration":238,"passed_time":0.4341090386,"remaining_time":1.382246772},
{"learn":[4.653242871],"iteration":239,"passed_time":0.4347576043,"remaining_time":1.376732414},
{"learn":[4.6507302],"iteration":240,"passed_time":0.4357570152,"remaining_time":1.37236338},
{"learn":[4.647671336],"iteration":241,"passed_time":0.4369036296,"remaining_time":1.36848327},
{"learn":[4.645506007],"iteration":242,"passed_time":0.4378870882,"remaining_time":1.36411739},
{"learn":[4.641297906],"iteration":243,"passed_time":0.4392313506,"remaining_time":1.360897136},
{"learn":[4.63798107],"iteration":244,"passed_time":0.4404554186,"remaining_time":1.3573218},
{"learn":[4.635062318],"iteration":245,"passed_time":0.4413298562,"remaining_time":1.352693949},
{"learn":[4.631606017],"iteration":246,"passed_time":0.4420919255,"remaining_time":1.347753927},
{"learn":[4.630215494],"iteration":247,"passed_time":0.4430328149,"remaining_time":1.343389826},
{"learn":[4.62729814],"iteration":248,"passed_time":0.4437003015,"remaining_time":1.33822862},
{"learn":[4.624691756],"iteration":249,"passed_time":0.4443172439,"remaining_time":1.332951732},
{"learn":[4.621840053],"iteration":250,"passed_time":0.4449113948,"remaining_time":1.327643963},
{"learn":[4.619602091],"iteration":251,"passed_time":0.4454754121,"remaining_time":1.32228416},
{"learn":[4.613584029],"iteration":252,"passed_time":0.4460761572,"remaining_time":1.317070709},
{"learn":[4.6119388],"iteration":253,"passed_time":0.4466604765,"remaining_time":1.311845337},
{"learn":[4.60870702],"iteration":254,"passed_time":0.4472979194,"remaining_time":1.306811569},
{"learn":[4.604771557],"iteration":255,"passed_time":0.4478969029,"remaining_time":1.301700374},
{"learn":[4.604231277],"iteration":256,"passed_time":0.4485217808,"remaining_time":1.296699156},
{"learn":[4.600750354],"iteration":257,"passed_time":0.4491069142,"remaining_time":1.291617559},
{"learn":[4.596488253],"iteration":258,"passed_time":0.4496852755,"remaining_time":1.286551309},
{"learn":[4.59470784],"iteration":259,"passed_time":0.4508525213,"remaining_time":1.283195638},
{"learn":[4.588818005],"iteration":260,"passed_time":0.4521288698,"remaining_time":1.28016565},
{"learn":[4.585054174],"iteration":261,"passed_time":0.4533880338,"remaining_time":1.277100645},
{"learn":[4.581471435],"iteration":262,"passed_time":0.454694044,"remaining_time":1.274180648},
{"learn":[4.577555199],"iteration":263,"passed_time":0.4557133904,"remaining_time":1.270473694},
{"learn":[4.57457145],"iteration":264,"passed_time":0.4567603,"remaining_time":1.266863474},
{"learn":[4.573029224],"iteration":265,"passed_time":0.457452697,"remaining_time":1.262294284},
{"learn":[4.571326203],"iteration":266,"passed_time":0.458136567,"remaining_time":1.257730725},
{"learn":[4.571019224],"iteration":267,"passed_time":0.4587541884,"remaining_time":1.253015171},
{"learn":[4.565766631],"iteration":268,"passed_time":0.4593904451,"remaining_time":1.248380726},
{"learn":[4.563383471],"iteration":269,"passed_time":0.4600384968,"remaining_time":1.243807788},
{"learn":[4.558165805],"iteration":270,"passed_time":0.4606733693,"remaining_time":1.239228363},
{"learn":[4.55629209],"iteration":271,"passed_time":0.4614398877,"remaining_time":1.235030288},
{"learn":[4.549383848],"iteration":272,"passed_time":0.462225068,"remaining_time":1.230907049},
{"learn":[4.546227503],"iteration":273,"passed_time":0.4628593939,"remaining_time":1.226408467},
{"learn":[4.540620977],"iteration":274,"passed_time":0.4634838361,"remaining_time":1.221911931},
{"learn":[4.532898237],"iteration":275,"passed_time":0.4641297866,"remaining_time":1.217499875},
{"learn":[4.529757367],"iteration":276,"passed_time":0.4653008065,"remaining_time":1.214485498},
{"learn":[4.52579294],"iteration":277,"passed_time":0.4662645518,"remaining_time":1.210946066},
{"learn":[4.521572155],"iteration":278,"passed_time":0.4675056096,"remaining_time":1.208141737},
{"learn":[4.518818099],"iteration":279,"passed_time":0.4686436849,"remaining_time":1.205083761},
{"learn":[4.514012334],"iteration":280,"passed_time":0.469995102,"remaining_time":1.202585332},
{"learn":[4.508331416],"iteration":281,"passed_time":0.4709797422,"remaining_time":1.199161188},
{"learn":[4.506038537],"iteration":282,"passed_time":0.4718937791,"remaining_time":1.195575405},
{"learn":[4.505805643],"iteration":283,"passed_time":0.4725335096,"remaining_time":1.191316876},
{"learn":[4.501550352],"iteration":284,"passed_time":0.4732034192,"remaining_time":1.187159455},
{"learn":[4.494692643],"iteration":285,"passed_time":0.4738485183,"remaining_time":1.182964483},
{"learn":[4.489330245],"iteration":286,"passed_time":0.4744701289,"remaining_time":1.178735895},
{"learn":[4.484826955],"iteration":287,"passed_time":0.4751135679,"remaining_time":1.174586321},
{"learn":[4.478285428],"iteration":288,"passed_time":0.4757583308,"remaining_time":1.170464267},
{"learn":[4.475311671],"iteration":289,"passed_time":0.476431989,"remaining_time":1.166436939},
{"learn":[4.471581298],"iteration":290,"passed_time":0.4772244225,"remaining_time":1.162722047},
{"learn":[4.469164956],"iteration":291,"passed_time":0.4779125837,"remaining_time":1.158774347},
{"learn":[4.462068024],"iteration":292,"passed_time":0.4786403118,"remaining_time":1.15494437},
{"learn":[4.458540976],"iteration":293,"passed_time":0.479349431,"remaining_time":1.15109081},
{"learn":[4.455757458],"iteration":294,"passed_time":0.4800178837,"remaining_time":1.147161383},
{"learn":[4.453027414],"iteration":295,"passed_time":0.4808536005,"remaining_time":1.143651807},
{"learn":[4.450659338],"iteration":296,"passed_time":0.4821513136,"remaining_time":1.141253783},
{"learn":[4.444696901],"iteration":297,"passed_time":0.4833816062,"remaining_time":1.138704321},
{"learn":[4.442052813],"iteration":298,"passed_time":0.4846368796,"remaining_time":1.13622225},
{"learn":[4.440036756],"iteration":299,"passed_time":0.4857138818,"remaining_time":1.133332391},
{"learn":[4.435017051],"iteration":300,"passed_time":0.486747763,"remaining_time":1.13035444},
{"learn":[4.429962125],"iteration":301,"passed_time":0.4876862237,"remaining_time":1.127168822},
{"learn":[4.427666256],"iteration":302,"passed_time":0.488360357,"remaining_time":1.123389996},
{"learn":[4.425030004],"iteration":303,"passed_time":0.4890237218,"remaining_time":1.119606942},
{"learn":[4.422588771],"iteration":304,"passed_time":0.4896374964,"remaining_time":1.115731344},
{"learn":[4.418936667],"iteration":305,"passed_time":0.4902655949,"remaining_time":1.111909552},
{"learn":[4.416887976],"iteration":306,"passed_time":0.4908977923,"remaining_time":1.108117818},
{"learn":[4.413773354],"iteration":307,"passed_time":0.4915660905,"remaining_time":1.10442771},
{"learn":[4.411129391],"iteration":308,"passed_time":0.492217417,"remaining_time":1.100719208},
{"learn":[4.40850819],"iteration":309,"passed_time":0.4928495368,"remaining_time":1.096987679},
{"learn":[4.404880292],"iteration":310,"passed_time":0.4934826564,"remaining_time":1.093278297},
{"learn":[4.404593827],"iteration":311,"passed_time":0.4941136948,"remaining_time":1.089584045},
{"learn":[4.402139942],"iteration":312,"passed_time":0.4947382032,"remaining_time":1.085895034},
{"learn":[4.400284725],"iteration":313,"passed_time":0.4958327679,"remaining_time":1.08325248},
{"learn":[4.395805521],"iteration":314,"passed_time":0.4971671153,"remaining_time":1.081141187},
{"learn":[4.392838833],"iteration":315,"passed_time":0.4983886479,"remaining_time":1.078790618},
{"learn":[4.389213061],"iteration":316,"passed_time":0.4996843363,"remaining_time":1.076606945},
{"learn":[4.3861981],"iteration":317,"passed_time":0.5007844494,"remaining_time":1.074009417},
{"learn":[4.385054234],"iteration":318,"passed_time":0.5017887721,"remaining_time":1.071216783},
{"learn":[4.379364607],"iteration":319,"passed_time":0.5024575229,"remaining_time":1.067722236},
{"learn":[4.378387619],"iteration":320,"passed_time":0.5031001479,"remaining_time":1.064190032},
{"learn":[4.375816727],"iteration":321,"passed_time":0.5037373455,"remaining_time":1.060664349},
{"learn":[4.374600202],"iteration":322,"passed_time":0.5043438555,"remaining_time":1.05709223},
{"learn":[4.37098897],"iteration":323,"passed_time":0.5049804269,"remaining_time":1.053601138},
{"learn":[4.367418484],"iteration":324,"passed_time":0.5056233554,"remaining_time":1.050140815},
{"learn":[4.363584638],"iteration":325,"passed_time":0.5062731353,"remaining_time":1.046711942},
{"learn":[4.360770706],"iteration":326,"passed_time":0.5069372593,"remaining_time":1.043329589},
{"learn":[4.358675808],"iteration":327,"passed_time":0.5075810459,"remaining_time":1.039922143},
{"learn":[4.354228195],"iteration":328,"passed_time":0.5082284774,"remaining_time":1.036538931},
{"learn":[4.353773425],"iteration":329,"passed_time":0.5088818763,"remaining_time":1.033184415},
{"learn":[4.351648009],"iteration":330,"passed_time":0.5096652478,"remaining_time":1.030108915},
{"learn":[4.348209927],"iteration":331,"passed_time":0.5104974664,"remaining_time":1.027145505},
{"learn":[4.345852733],"iteration":332,"passed_time":0.5114612054,"remaining_time":1.02445833},
{"learn":[4.34237339],"iteration":333,"passed_time":0.5125028394,"remaining_time":1.021936799},
{"learn":[4.340814362],"iteration":334,"passed_time":0.5136276691,"remaining_time":1.019589254},
{"learn":[4.339707068],"iteration":335,"passed_time":0.5145802473,"remaining_time":1.016908584},
{"learn":[4.335430786],"iteration":336,"passed_time":0.5156761129,"remaining_time":1.014520068},
{"learn":[4.33521887],"iteration":337,"passed_time":0.5164993914,"remaining_time":1.011605317},
{"learn":[4.328507238],"iteration":338,"passed_time":0.517152664,"remaining_time":1.008371419},
{"learn":[4.326140732],"iteration":339,"passed_time":0.5177840259,"remaining_time":1.005110168},
{"learn":[4.323785636],"iteration":340,"passed_time":0.5183498283,"remaining_time":1.001737645},
{"learn":[4.320632534],"iteration":341,"passed_time":0.5189397715,"remaining_time":0.9984279813},
{"learn":[4.31973724],"iteration":342,"passed_time":0.5195357876,"remaining_time":0.9951458089},
{"learn":[4.318000924],"iteration":343,"passed_time":0.5201487943,"remaining_time":0.9919116542},
{"learn":[4.312713628],"iteration":344,"passed_time":0.5208653939,"remaining_time":0.9888893711},
{"learn":[4.308220789],"iteration":345,"passed_time":0.5215960238,"remaining_time":0.9859069352},
{"learn":[4.305890947],"iteration":346,"passed_time":0.5222552484,"remaining_time":0.9828031043},
{"learn":[4.305137856],"iteration":347,"passed_time":0.5228854555,"remaining_time":0.9796589568},
{"learn":[4.304787172],"iteration":348,"passed_time":0.5235518217,"remaining_time":0.9765966645},
{"learn":[4.30350134],"iteration":349,"passed_time":0.5241744601,"remaining_time":0.9734668544},
{"learn":[4.30293809],"iteration":350,"passed_time":0.524830728,"remaining_time":0.9704135114},
{"learn":[4.299548459],"iteration":351,"passed_time":0.5257509134,"remaining_time":0.967859636},
{"learn":[4.294768408],"iteration":352,"passed_time":0.5268705219,"remaining_time":0.9656805316},
{"learn":[4.294581479],"iteration":353,"passed_time":0.5277493283,"remaining_time":0.9630679832},
{"learn":[4.292551604],"iteration":354,"passed_time":0.5291672161,"remaining_time":0.9614446603},
{"learn":[4.288628894],"iteration":355,"passed_time":0.530209893,"remaining_time":0.9591437391},
{"learn":[4.287802767],"iteration":356,"passed_time":0.5310674497,"remaining_time":0.956516443},
{"learn":[4.284566905],"iteration":357,"passed_time":0.531849507,"remaining_time":0.9537636411},
{"learn":[4.27890232],"iteration":358,"passed_time":0.532660792,"remaining_time":0.9510740046},
{"learn":[4.276938023],"iteration":359,"passed_time":0.5333447923,"remaining_time":0.9481685196},
{"learn":[4.273425094],"iteration":360,"passed_time":0.5339967383,"remaining_time":0.9452186032},
{"learn":[4.269726505],"iteration":361,"passed_time":0.5346266533,"remaining_time":0.9422425547},
{"learn":[4.265565857],"iteration":362,"passed_time":0.5352651702,"remaining_time":0.9392945273},
{"learn":[4.262117173],"iteration":363,"passed_time":0.5359284133,"remaining_time":0.9364023925},
{"learn":[4.259185148],"iteration":364,"passed_time":0.5365811452,"remaining_time":0.9335041842},
{"learn":[4.257668507],"iteration":365,"passed_time":0.5372179018,"remaining_time":0.930590573},
{"learn":[4.253432436],"iteration":366,"passed_time":0.5378685847,"remaining_time":0.9277133899},
{"learn":[4.250216667],"iteration":367,"passed_time":0.5385089675,"remaining_time":0.924830618},
{"learn":[4.24514828],"iteration":368,"passed_time":0.5391847836,"remaining_time":0.922020592},
{"learn":[4.244015772],"iteration":369,"passed_time":0.539850277,"remaining_time":0.9192045257},
{"learn":[4.240329192],"iteration":370,"passed_time":0.5409071873,"remaining_time":0.9170636679},
{"learn":[4.236718014],"iteration":371,"passed_time":0.5422516048,"remaining_time":0.9154139994},
{"learn":[4.233495944],"iteration":372,"passed_time":0.5434878163,"remaining_time":0.9135840772},
{"learn":[4.230357491],"iteration":373,"passed_time":0.54462011,"remaining_time":0.9115833927},
{"learn":[4.227381215],"iteration":374,"passed_time":0.5455479552,"remaining_time":0.9092465921},
{"learn":[4.226169067],"iteration":375,"passed_time":0.5462137941,"remaining_time":0.9064824668},
{"learn":[4.225963861],"iteration":376,"passed_time":0.5468375967,"remaining_time":0.9036600073},
{"learn":[4.224346548],"iteration":377,"passed_time":0.5474850116,"remaining_time":0.9008880349},
{"learn":[4.222595381],"iteration":378,"passed_time":0.5481025521,"remaining_time":0.8980783241},
{"learn":[4.219700938],"iteration":379,"passed_time":0.5487278711,"remaining_time":0.8952928423},
{"learn":[4.216356207],"iteration":380,"passed_time":0.5493552145,"remaining_time":0.8925219888},
{"learn":[4.214326494],"iteration":381,"passed_time":0.5499818781,"remaining_time":0.8897612583},
{"learn":[4.212901398],"iteration":382,"passed_time":0.5506306697,"remaining_time":0.887047319},
{"learn":[4.211331091],"iteration":383,"passed_time":0.5512938834,"remaining_time":0.8843672713},
{"learn":[4.208624791],"iteration":384,"passed_time":0.5520825126,"remaining_time":0.8818980395},
{"learn":[4.204659106],"iteration":385,"passed_time":0.5527348722,"remaining_time":0.8792207553},
{"learn":[4.202968852],"iteration":386,"passed_time":0.5533291708,"remaining_time":0.8764619682},
{"learn":[4.197261935],"iteration":387,"passed_time":0.5539512966,"remaining_time":0.8737582308},
{"learn":[4.196934403],"iteration":388,"passed_time":0.5545878517,"remaining_time":0.8710878596},
{"learn":[4.192479929],"iteration":389,"passed_time":0.5574442058,"remaining_time":0.8718999117},
{"learn":[4.190243116],"iteration":390,"passed_time":0.5586170355,"remaining_time":0.8700710348},
{"learn":[4.185852431],"iteration":391,"passed_time":0.5600054551,"remaining_time":0.8685798895},
{"learn":[4.180967944],"iteration":392,"passed_time":0.5611216274,"remaining_time":0.8666687731},
{"learn":[4.178283162],"iteration":393,"passed_time":0.5617943105,"remaining_time":0.864079574},
{"learn":[4.176341157],"iteration":394,"passed_time":0.5624522025,"remaining_time":0.861477424},
{"learn":[4.176041504],"iteration":395,"passed_time":0.5630534448,"remaining_time":0.8587986886},
{"learn":[4.175564513],"iteration":396,"passed_time":0.5636589557,"remaining_time":0.8561369025},
{"learn":[4.170830274],"iteration":397,"passed_time":0.5643191854,"remaining_time":0.8535682151},
{"learn":[4.167804808],"iteration":398,"passed_time":0.5649596772,"remaining_time":0.8509793634},
{"learn":[4.165860548],"iteration":399,"passed_time":0.5655912844,"remaining_time":0.8483869265},
{"learn":[4.160950571],"iteration":400,"passed_time":0.5662488963,"remaining_time":0.8458431144},
{"learn":[4.158544115],"iteration":401,"passed_time":0.5668915901,"remaining_time":0.8432864948},
{"learn":[4.154448767],"iteration":402,"passed_time":0.5675410781,"remaining_time":0.8407494382},
{"learn":[4.15197457],"iteration":403,"passed_time":0.5681712571,"remaining_time":0.8381932406},
{"learn":[4.149562679],"iteration":404,"passed_time":0.5688169797,"remaining_time":0.8356693899},
{"learn":[4.149327961],"iteration":405,"passed_time":0.5696413306,"remaining_time":0.8334161339},
{"learn":[4.147444889],"iteration":406,"passed_time":0.5705467632,"remaining_time":0.8312880359},
{"learn":[4.147254809],"iteration":407,"passed_time":0.571466295,"remaining_time":0.8291863888},
{"learn":[4.144589165],"iteration":408,"passed_time":0.572529863,"remaining_time":0.8272986529},
{"learn":[4.141691034],"iteration":409,"passed_time":0.5737197056,"remaining_time":0.8255966495},
{"learn":[4.138893468],"iteration":410,"passed_time":0.5745732738,"remaining_time":0.8234152269},
{"learn":[4.136964597],"iteration":411,"passed_time":0.5753949734,"remaining_time":0.8211947679},
{"learn":[4.133773523],"iteration":412,"passed_time":0.5761451087,"remaining_time":0.8188793676},
{"learn":[4.131363444],"iteration":413,"passed_time":0.5768383371,"remaining_time":0.8164909795},
{"learn":[4.130228592],"iteration":414,"passed_time":0.5775003091,"remaining_time":0.8140667008},
{"learn":[4.12884186],"iteration":415,"passed_time":0.5781927058,"remaining_time":0.8116936062},
{"learn":[4.12413494],"iteration":416,"passed_time":0.5788785185,"remaining_time":0.8093193676},
{"learn":[4.119422508],"iteration":417,"passed_time":0.5795147658,"remaining_time":0.8068841955},
{"learn":[4.117038244],"iteration":418,"passed_time":0.5801606562,"remaining_time":0.8044709815},
{"learn":[4.116067631],"iteration":419,"passed_time":0.5807585477,"remaining_time":0.8019998991},
{"learn":[4.110343455],"iteration":420,"passed_time":0.5813992499,"remaining_time":0.7995965931},
{"learn":[4.105604544],"iteration":421,"passed_time":0.5820201915,"remaining_time":0.7971745751},
{"learn":[4.103390131],"iteration":422,"passed_time":0.5826465277,"remaining_time":0.7947684314},
{"learn":[4.096724402],"iteration":423,"passed_time":0.5832495538,"remaining_time":0.7923390165},
{"learn":[4.093431279],"iteration":424,"passed_time":0.5840659928,"remaining_time":0.7902069314},
{"learn":[4.091412744],"iteration":425,"passed_time":0.5847151185,"remaining_time":0.7878555822},
{"learn":[4.091192901],"iteration":426,"passed_time":0.5855945581,"remaining_time":0.7858212688},
{"learn":[4.088994581],"iteration":427,"passed_time":0.586536211,"remaining_time":0.783875497},
{"learn":[4.087845355],"iteration":428,"passed_time":0.5876756664,"remaining_time":0.7821976819},
{"learn":[4.083650279],"iteration":429,"passed_time":0.5887739925,"remaining_time":0.7804678505},
{"learn":[4.079840652],"iteration":430,"passed_time":0.5896996737,"remaining_time":0.7785130263},
{"learn":[4.075707828],"iteration":431,"passed_time":0.5904729868,"remaining_time":0.7763626307},
{"learn":[4.071345409],"iteration":432,"passed_time":0.5911164291,"remaining_time":0.7740485342},
{"learn":[4.067460475],"iteration":433,"passed_time":0.5917786658,"remaining_time":0.7717666471},
{"learn":[4.064914749],"iteration":434,"passed_time":0.592437216,"remaining_time":0.7694874185},
{"learn":[4.063823175],"iteration":435,"passed_time":0.5930530644,"remaining_time":0.7671603861},
{"learn":[4.058898471],"iteration":436,"passed_time":0.5937087209,"remaining_time":0.764892471},
{"learn":[4.054120355],"iteration":437,"passed_time":0.594341922,"remaining_time":0.7626031054},
{"learn":[4.052715901],"iteration":438,"passed_time":0.5949840898,"remaining_time":0.7603327435},
{"learn":[4.052114167],"iteration":439,"passed_time":0.5955970003,"remaining_time":0.7580325458},
{"learn":[4.051377267],"iteration":440,"passed_time":0.5962269715,"remaining_time":0.7557616259},
{"learn":[4.049275336],"iteration":441,"passed_time":0.5968510768,"remaining_time":0.7534907259},
{"learn":[4.047099198],"iteration":442,"passed_time":0.5974842913,"remaining_time":0.7512387139},
{"learn":[4.044348685],"iteration":443,"passed_time":0.5982620831,"remaining_time":0.749175041},
{"learn":[4.042822379],"iteration":444,"passed_time":0.5989182515,"remaining_time":0.7469654597},
{"learn":[4.041258611],"iteration":445,"passed_time":0.5995717265,"remaining_time":0.7447594989},
{"learn":[4.040044254],"iteration":446,"passed_time":0.6002223813,"remaining_time":0.7425569953},
{"learn":[4.036860137],"iteration":447,"passed_time":0.6011256126,"remaining_time":0.7406726298},
{"learn":[4.036372284],"iteration":448,"passed_time":0.6021100663,"remaining_time":0.7388923086},
{"learn":[4.03368231],"iteration":449,"passed_time":0.6031925099,"remaining_time":0.7372352899},
{"learn":[4.032439519],"iteration":450,"passed_time":0.6043951369,"remaining_time":0.7357271179},
{"learn":[4.032008634],"iteration":451,"passed_time":0.6052218697,"remaining_time":0.7337645677},
{"learn":[4.030034932],"iteration":452,"passed_time":0.6059180293,"remaining_time":0.7316493643},
{"learn":[4.028173412],"iteration":453,"passed_time":0.606659005,"remaining_time":0.72959431},
{"learn":[4.023806097],"iteration":454,"passed_time":0.60728079,"remaining_time":0.7274022649},
{"learn":[4.020239186],"iteration":455,"passed_time":0.6078895308,"remaining_time":0.7252015455},
{"learn":[4.017384838],"iteration":456,"passed_time":0.6084544877,"remaining_time":0.7229557699},
{"learn":[4.016468229],"iteration":457,"passed_time":0.609044463,"remaining_time":0.7207469409},
{"learn":[4.014530169],"iteration":458,"passed_time":0.6097132348,"remaining_time":0.7186380393},
{"learn":[4.012884822],"iteration":459,"passed_time":0.6103655109,"remaining_time":0.7165160345},
{"learn":[4.008924707],"iteration":460,"passed_time":0.610983842,"remaining_time":0.7143607177},
{"learn":[4.008286778],"iteration":461,"passed_time":0.6116086786,"remaining_time":0.71221963},
{"learn":[4.006444202],"iteration":462,"passed_time":0.6123629363,"remaining_time":0.7102351983},
{"learn":[4.003284363],"iteration":463,"passed_time":0.6130178817,"remaining_time":0.7081413461},
{"learn":[3.999811484],"iteration":464,"passed_time":0.6136696746,"remaining_time":0.7060500558},
{"learn":[3.997483319],"iteration":465,"passed_time":0.6143409777,"remaining_time":0.7039873006},
{"learn":[3.99708333],"iteration":466,"passed_time":0.6149888529,"remaining_time":0.7019037658},
{"learn":[3.995860263],"iteration":467,"passed_time":0.6158914115,"remaining_time":0.700115878},
{"learn":[3.994131111],"iteration":468,"passed_time":0.6169131815,"remaining_time":0.6984667365},
{"learn":[3.993125499],"iteration":469,"passed_time":0.6178061281,"remaining_time":0.6966749955},
{"learn":[3.992954084],"iteration":470,"passed_time":0.6185661026,"remaining_time":0.6947377246},
{"learn":[3.990635743],"iteration":471,"passed_time":0.6193432381,"remaining_time":0.6928246393},
{"learn":[3.986678254],"iteration":472,"passed_time":0.6273242979,"remaining_time":0.6989427167},
{"learn":[3.986393291],"iteration":473,"passed_time":0.6279858502,"remaining_time":0.6968788127},
{"learn":[3.986152671],"iteration":474,"passed_time":0.6286161127,"remaining_time":0.6947862299},
{"learn":[3.985596662],"iteration":475,"passed_time":0.629219767,"remaining_time":0.6926704998},
{"learn":[3.983853457],"iteration":476,"passed_time":0.6298561801,"remaining_time":0.6905970276},
{"learn":[3.983263928],"iteration":477,"passed_time":0.6304592442,"remaining_time":0.6884931496},
{"learn":[3.980067202],"iteration":478,"passed_time":0.6313376446,"remaining_time":0.6866950164},
{"learn":[3.978115407],"iteration":479,"passed_time":0.6323996217,"remaining_time":0.6850995902},
{"learn":[3.972661644],"iteration":480,"passed_time":0.6334515531,"remaining_time":0.6834955428},
{"learn":[3.969938254],"iteration":481,"passed_time":0.6343774388,"remaining_time":0.6817583264},
{"learn":[3.968211434],"iteration":482,"passed_time":0.6351835782,"remaining_time":0.6798962938},
{"learn":[3.966113368],"iteration":483,"passed_time":0.6358724424,"remaining_time":0.6779135957},
{"learn":[3.962246044],"iteration":484,"passed_time":0.6365309098,"remaining_time":0.6759039558},
{"learn":[3.961319703],"iteration":485,"passed_time":0.6371796873,"remaining_time":0.6738896282},
{"learn":[3.96078191],"iteration":486,"passed_time":0.6377925283,"remaining_time":0.6718430534},
{"learn":[3.958913633],"iteration":487,"passed_time":0.6384158925,"remaining_time":0.6698133954},
{"learn":[3.957428286],"iteration":488,"passed_time":0.6390886671,"remaining_time":0.6678411225},
{"learn":[3.952641965],"iteration":489,"passed_time":0.6397135638,"remaining_time":0.6658243215},
{"learn":[3.951486786],"iteration":490,"passed_time":0.6403714711,"remaining_time":0.663847411},
{"learn":[3.94938344],"iteration":491,"passed_time":0.6410162541,"remaining_time":0.6618623111},
{"learn":[3.947297924],"iteration":492,"passed_time":0.6417216705,"remaining_time":0.659945004},
{"learn":[3.946284886],"iteration":493,"passed_time":0.6424131499,"remaining_time":0.6580183277},
{"learn":[3.943288204],"iteration":494,"passed_time":0.6431190883,"remaining_time":0.6561113931},
{"learn":[3.943076488],"iteration":495,"passed_time":0.6437411199,"remaining_time":0.6541240412},
{"learn":[3.942347078],"iteration":496,"passed_time":0.6445443166,"remaining_time":0.6523255357},
{"learn":[3.940251541],"iteration":497,"passed_time":0.6452663831,"remaining_time":0.6504492456},
{"learn":[3.939011019],"iteration":498,"passed_time":0.6458838908,"remaining_time":0.6484726038},
{"learn":[3.938760512],"iteration":499,"passed_time":0.6467704239,"remaining_time":0.6467704239},
{"learn":[3.934522727],"iteration":500,"passed_time":0.6479330591,"remaining_time":0.6453465},
{"learn":[3.930091193],"iteration":501,"passed_time":0.6488825059,"remaining_time":0.6437121274},
{"learn":[3.927671752],"iteration":502,"passed_time":0.6499822237,"remaining_time":0.6422289566},
{"learn":[3.927280041],"iteration":503,"passed_time":0.6509203225,"remaining_time":0.6405882539},
{"learn":[3.925987561],"iteration":504,"passed_time":0.651744939,"remaining_time":0.6388390987},
{"learn":[3.921645957],"iteration":505,"passed_time":0.6524703888,"remaining_time":0.6369967828},
{"learn":[3.920333743],"iteration":506,"passed_time":0.653094021,"remaining_time":0.6350598666},
{"learn":[3.918659461],"iteration":507,"passed_time":0.6537112515,"remaining_time":0.6331219207},
{"learn":[3.916124385],"iteration":508,"passed_time":0.6543564087,"remaining_time":0.6312161035},
{"learn":[3.913849268],"iteration":509,"passed_time":0.654977764,"remaining_time":0.6292923614},
{"learn":[3.912826119],"iteration":510,"passed_time":0.655624576,"remaining_time":0.6273980776},
{"learn":[3.910034145],"iteration":511,"passed_time":0.6562483679,"remaining_time":0.6254867256},
{"learn":[3.90792379],"iteration":512,"passed_time":0.6569567342,"remaining_time":0.6236606814},
{"learn":[3.907823851],"iteration":513,"passed_time":0.6575620219,"remaining_time":0.6217415226},
{"learn":[3.904527401],"iteration":514,"passed_time":0.6582102895,"remaining_time":0.6198679425},
{"learn":[3.903378283],"iteration":515,"passed_time":0.6588558023,"remaining_time":0.6179965277},
{"learn":[3.902170135],"iteration":516,"passed_time":0.6594682616,"remaining_time":0.6160989755},
{"learn":[3.899435429],"iteration":517,"passed_time":0.6601355728,"remaining_time":0.6142574249},
{"learn":[3.897497505],"iteration":518,"passed_time":0.6607544934,"remaining_time":0.6123755517},
{"learn":[3.896426119],"iteration":519,"passed_time":0.6616967755,"remaining_time":0.6107970236},
{"learn":[3.896044669],"iteration":520,"passed_time":0.6627294621,"remaining_time":0.6093040544},
{"learn":[3.892795942],"iteration":521,"passed_time":0.6639530933,"remaining_time":0.6079876984},
{"learn":[3.892413888],"iteration":522,"passed_time":0.6649972886,"remaining_time":0.6065080433},
{"learn":[3.891738985],"iteration":523,"passed_time":0.6658820369,"remaining_time":0.6048852091},
{"learn":[3.88822057],"iteration":524,"passed_time":0.6666842522,"remaining_time":0.6031905139},
{"learn":[3.883837053],"iteration":525,"passed_time":0.6675307774,"remaining_time":0.6015391416},
{"learn":[3.881769742],"iteration":526,"passed_time":0.668186363,"remaining_time":0.5997194492},
{"learn":[3.880356898],"iteration":527,"passed_time":0.66887657,"remaining_time":0.5979351156},
{"learn":[3.879250273],"iteration":528,"passed_time":0.6695920959,"remaining_time":0.5961774616},
{"learn":[3.877174493],"iteration":529,"passed_time":0.6702512878,"remaining_time":0.5943737835},
{"learn":[3.875854201],"iteration":530,"passed_time":0.6708878037,"remaining_time":0.5925543879},
{"learn":[3.873189396],"iteration":531,"passed_time":0.6715225279,"remaining_time":0.5907378629},
{"learn":[3.871583368],"iteration":532,"passed_time":0.6721572521,"remaining_time":0.5889257725},
{"learn":[3.869622679],"iteration":533,"passed_time":0.6730086045,"remaining_time":0.5873071343},
{"learn":[3.866860164],"iteration":534,"passed_time":0.6736933159,"remaining_time":0.5855465269},
{"learn":[3.864498444],"iteration":535,"passed_time":0.6743345869,"remaining_time":0.583752329},
{"learn":[3.861416322],"iteration":536,"passed_time":0.6750018841,"remaining_time":0.5819848647},
{"learn":[3.860265769],"iteration":537,"passed_time":0.6756083065,"remaining_time":0.5801692149},
{"learn":[3.859328725],"iteration":538,"passed_time":0.6764604445,"remaining_time":0.5785682095},
{"learn":[3.858521278],"iteration":539,"passed_time":0.6776041761,"remaining_time":0.5772183723},
{"learn":[3.85599111],"iteration":540,"passed_time":0.6786067478,"remaining_time":0.5757495328},
{"learn":[3.852379816],"iteration":541,"passed_time":0.6794962325,"remaining_time":0.5741868533},
{"learn":[3.851327537],"iteration":542,"passed_time":0.6803191793,"remaining_time":0.5725706536},
{"learn":[3.847854898],"iteration":543,"passed_time":0.6810131247,"remaining_time":0.5708492369},
{"learn":[3.847083414],"iteration":544,"passed_time":0.6816446578,"remaining_time":0.5690794849},
{"learn":[3.845397429],"iteration":545,"passed_time":0.6822902741,"remaining_time":0.5673256126},
{"learn":[3.841933528],"iteration":546,"passed_time":0.6829288251,"remaining_time":0.5655699411},
{"learn":[3.840996474],"iteration":547,"passed_time":0.6836503268,"remaining_time":0.5638867659},
{"learn":[3.838355966],"iteration":548,"passed_time":0.6843283477,"remaining_time":0.5621713749},
{"learn":[3.83342799],"iteration":549,"passed_time":0.6849846712,"remaining_time":0.5604420037},
{"learn":[3.828161535],"iteration":550,"passed_time":0.6856465837,"remaining_time":0.5587210818},
{"learn":[3.823502399],"iteration":551,"passed_time":0.686279303,"remaining_time":0.5569803039},
{"learn":[3.820068862],"iteration":552,"passed_time":0.6869403801,"remaining_time":0.5552664555},
{"learn":[3.817951642],"iteration":553,"passed_time":0.6876178677,"remaining_time":0.5535696191},
{"learn":[3.815785958],"iteration":554,"passed_time":0.6882790665,"remaining_time":0.5518633956},
{"learn":[3.81503012],"iteration":555,"passed_time":0.6889519273,"remaining_time":0.5501702441},
{"learn":[3.813529315],"iteration":556,"passed_time":0.689603896,"remaining_time":0.5484641399},
{"learn":[3.808881326],"iteration":557,"passed_time":0.6904731686,"remaining_time":0.5469339436},
{"learn":[3.808740434],"iteration":558,"passed_time":0.6911186219,"remaining_time":0.5452295389},
{"learn":[3.80714352],"iteration":559,"passed_time":0.6919914118,"remaining_time":0.5437075378},
{"learn":[3.80573346],"iteration":560,"passed_time":0.692980908,"remaining_time":0.5422791775},
{"learn":[3.803370052],"iteration":561,"passed_time":0.6939959421,"remaining_time":0.5408722822},
{"learn":[3.803215211],"iteration":562,"passed_time":0.6951089991,"remaining_time":0.5395428643},
{"learn":[3.801309667],"iteration":563,"passed_time":0.696012779,"remaining_time":0.538052432},
{"learn":[3.800003847],"iteration":564,"passed_time":0.6966982369,"remaining_time":0.5363959877},
{"learn":[3.798026138],"iteration":565,"passed_time":0.6973596114,"remaining_time":0.5347245077},
{"learn":[3.794745847],"iteration":566,"passed_time":0.698026406,"remaining_time":0.5330607298},
{"learn":[3.794312041],"iteration":567,"passed_time":0.6986394488,"remaining_time":0.5313595808},
{"learn":[3.792205926],"iteration":568,"passed_time":0.6992793878,"remaining_time":0.5296826294},
{"learn":[3.788991061],"iteration":569,"passed_time":0.6999161958,"remaining_time":0.5280069548},
{"learn":[3.787391572],"iteration":570,"passed_time":0.700538333,"remaining_time":0.5263238964},
{"learn":[3.7826445],"iteration":571,"passed_time":0.7011836634,"remaining_time":0.524661902},
{"learn":[3.781700331],"iteration":572,"passed_time":0.7018134106,"remaining_time":0.5229918435},
{"learn":[3.780045374],"iteration":573,"passed_time":0.7024564854,"remaining_time":0.521335301},
{"learn":[3.775462644],"iteration":574,"passed_time":0.7031135513,"remaining_time":0.5196926249},
{"learn":[3.773711943],"iteration":575,"passed_time":0.7037796957,"remaining_time":0.5180600537},
{"learn":[3.772415806],"iteration":576,"passed_time":0.7044096454,"remaining_time":0.5164042981},
{"learn":[3.770170875],"iteration":577,"passed_time":0.7051712757,"remaining_time":0.5148482324},
{"learn":[3.765166479],"iteration":578,"passed_time":0.7058533205,"remaining_time":0.5132370431},
{"learn":[3.763976102],"iteration":579,"passed_time":0.7066811282,"remaining_time":0.5117346101},
{"learn":[3.760761708],"iteration":580,"passed_time":0.7077096178,"remaining_time":0.5103792252},
{"learn":[3.758155662],"iteration":581,"passed_time":0.7086231926,"remaining_time":0.5089424304},
{"learn":[3.756844548],"iteration":582,"passed_time":0.7094310351,"remaining_time":0.5074318038},
{"learn":[3.753098923],"iteration":583,"passed_time":0.7103137233,"remaining_time":0.5059768988},
{"learn":[3.751618946],"iteration":584,"passed_time":0.7110178499,"remaining_time":0.5043972781},
{"learn":[3.751398464],"iteration":585,"passed_time":0.711697845,"remaining_time":0.502803597},
{"learn":[3.749920103],"iteration":586,"passed_time":0.7124181267,"remaining_time":0.5012413737},
{"learn":[3.748237465],"iteration":587,"passed_time":0.7131472121,"remaining_time":0.4996881827},
{"learn":[3.746021536],"iteration":588,"passed_time":0.7137845875,"remaining_time":0.4980737954},
{"learn":[3.74417648],"iteration":589,"passed_time":0.7144213073,"remaining_time":0.4964622644},
{"learn":[3.738788389],"iteration":590,"passed_time":0.715057703,"remaining_time":0.494853808},
{"learn":[3.736021611],"iteration":591,"passed_time":0.7156796357,"remaining_time":0.4932386678},
{"learn":[3.734546151],"iteration":592,"passed_time":0.7163331141,"remaining_time":0.4916485286},
{"learn":[3.733527479],"iteration":593,"passed_time":0.7169640697,"remaining_time":0.4900461486},
{"learn":[3.733026392],"iteration":594,"passed_time":0.7175787064,"remaining_time":0.4884359262},
{"learn":[3.730314752],"iteration":595,"passed_time":0.7182174953,"remaining_time":0.4868454163},
{"learn":[3.727342596],"iteration":596,"passed_time":0.7190488881,"remaining_time":0.4853881104},
{"learn":[3.725459604],"iteration":597,"passed_time":0.7197207606,"remaining_time":0.4838256618},
{"learn":[3.723158842],"iteration":598,"passed_time":0.720377372,"remaining_time":0.4822559703},
{"learn":[3.722362756],"iteration":599,"passed_time":0.7210024003,"remaining_time":0.4806682669},
{"learn":[3.721443615],"iteration":600,"passed_time":0.7219051945,"remaining_time":0.4792681741},
{"learn":[3.720743486],"iteration":601,"passed_time":0.7230578655,"remaining_time":0.4780349343},
{"learn":[3.720215334],"iteration":602,"passed_time":0.723863154,"remaining_time":0.476573254},
{"learn":[3.719436563],"iteration":603,"passed_time":0.7245896935,"remaining_time":0.4750621169},
{"learn":[3.715046574],"iteration":604,"passed_time":0.7253145692,"remaining_time":0.4735524873},
{"learn":[3.71443396],"iteration":605,"passed_time":0.725970527,"remaining_time":0.4720006397},
{"learn":[3.712938941],"iteration":606,"passed_time":0.7266165384,"remaining_time":0.4704453041},
{"learn":[3.712814764],"iteration":607,"passed_time":0.7272185219,"remaining_time":0.4688645733},
{"learn":[3.71235348],"iteration":608,"passed_time":0.7278704973,"remaining_time":0.4673191534},
{"learn":[3.711223749],"iteration":609,"passed_time":0.7284728805,"remaining_time":0.4657449564},
{"learn":[3.710755648],"iteration":610,"passed_time":0.729093943,"remaining_time":0.4641858328},
{"learn":[3.708668039],"iteration":611,"passed_time":0.7297544233,"remaining_time":0.4626547651},
{"learn":[3.705623591],"iteration":612,"passed_time":0.7303897764,"remaining_time":0.4611106745},
{"learn":[3.704045802],"iteration":613,"passed_time":0.731189943,"remaining_time":0.4596731564},
{"learn":[3.699915209],"iteration":614,"passed_time":0.7318522278,"remaining_time":0.4581513946},
{"learn":[3.696182221],"iteration":615,"passed_time":0.7325355638,"remaining_time":0.4566455463},
{"learn":[3.694263278],"iteration":616,"passed_time":0.7333433859,"remaining_time":0.4552196383},
{"learn":[3.693810229],"iteration":617,"passed_time":0.7340664258,"remaining_time":0.4537433247},
{"learn":[3.690900932],"iteration":618,"passed_time":0.7347026925,"remaining_time":0.4522160353},
{"learn":[3.688020895],"iteration":619,"passed_time":0.7353519605,"remaining_time":0.4506995887},
{"learn":[3.685491894],"iteration":620,"passed_time":0.7360036351,"remaining_time":0.4491874037},
{"learn":[3.684328128],"iteration":621,"passed_time":0.7369041858,"remaining_time":0.4478292319},
{"learn":[3.680640153],"iteration":622,"passed_time":0.7379216325,"remaining_time":0.4465432672},
{"learn":[3.678932783],"iteration":623,"passed_time":0.7387945978,"remaining_time":0.4451711038},
{"learn":[3.674167041],"iteration":624,"passed_time":0.7396268729,"remaining_time":0.4437761237},
{"learn":[3.672200976],"iteration":625,"passed_time":0.740506784,"remaining_time":0.4424114013},
{"learn":[3.670606604],"iteration":626,"passed_time":0.7412356849,"remaining_time":0.4409583899},
{"learn":[3.665506042],"iteration":627,"passed_time":0.7418886481,"remaining_time":0.4394627024},
{"learn":[3.664214007],"iteration":628,"passed_time":0.7425576213,"remaining_time":0.4379791375},
{"learn":[3.66261643],"iteration":629,"passed_time":0.7431711667,"remaining_time":0.4364656058},
{"learn":[3.662118449],"iteration":630,"passed_time":0.7437793568,"remaining_time":0.434951795},
{"learn":[3.660871366],"iteration":631,"passed_time":0.7444205664,"remaining_time":0.4334600766},
{"learn":[3.656695243],"iteration":632,"passed_time":0.7450670449,"remaining_time":0.4319741003},
{"learn":[3.654497801],"iteration":633,"passed_time":0.7457420463,"remaining_time":0.4305072381},
{"learn":[3.654189134],"iteration":634,"passed_time":0.7463515243,"remaining_time":0.4290052069},
{"learn":[3.653957699],"iteration":635,"passed_time":0.7469509308,"remaining_time":0.4275002183},
{"learn":[3.651920725],"iteration":636,"passed_time":0.7478871724,"remaining_time":0.4261900213},
{"learn":[3.65106705],"iteration":637,"passed_time":0.7487301194,"remaining_time":0.4248280615},
{"learn":[3.650612844],"iteration":638,"passed_time":0.7494839378,"remaining_time":0.4234173733},
{"learn":[3.649884732],"iteration":639,"passed_time":0.7501874328,"remaining_time":0.4219804309},
{"learn":[3.646276182],"iteration":640,"passed_time":0.7509124963,"remaining_time":0.4205578567},
{"learn":[3.645808194],"iteration":641,"passed_time":0.751900034,"remaining_time":0.4192838196},
{"learn":[3.645042989],"iteration":642,"passed_time":0.7538033535,"remaining_time":0.4185191247},
{"learn":[3.639864499],"iteration":643,"passed_time":0.7555895778,"remaining_time":0.4176861641},
{"learn":[3.637318478],"iteration":644,"passed_time":0.7568328954,"remaining_time":0.4165514386},
{"learn":[3.636344905],"iteration":645,"passed_time":0.7579147579,"remaining_time":0.4153279014},
{"learn":[3.634754643],"iteration":646,"passed_time":0.7587582492,"remaining_time":0.413974748},
{"learn":[3.630724975],"iteration":647,"passed_time":0.759624762,"remaining_time":0.4126356732},
{"learn":[3.629408252],"iteration":648,"passed_time":0.7603846767,"remaining_time":0.411240403},
{"learn":[3.62790646],"iteration":649,"passed_time":0.7611489281,"remaining_time":0.4098494228},
{"learn":[3.627388973],"iteration":650,"passed_time":0.7618997778,"remaining_time":0.4084531835},
{"learn":[3.625163557],"iteration":651,"passed_time":0.7626503843,"remaining_time":0.4070587941},
{"learn":[3.623701985],"iteration":652,"passed_time":0.7634145528,"remaining_time":0.4056735832},
{"learn":[3.622342639],"iteration":653,"passed_time":0.7641473955,"remaining_time":0.4042736985},
{"learn":[3.621130639],"iteration":654,"passed_time":0.7648788434,"remaining_time":0.402875116},
{"learn":[3.619125665],"iteration":655,"passed_time":0.7656218738,"remaining_time":0.4014846412},
{"learn":[3.618878783],"iteration":656,"passed_time":0.766733228,"remaining_time":0.400288428},
{"learn":[3.616207429],"iteration":657,"passed_time":0.7683461228,"remaining_time":0.399353152},
{"learn":[3.61206486],"iteration":658,"passed_time":0.7695007075,"remaining_time":0.3981786665},
{"learn":[3.611955873],"iteration":659,"passed_time":0.7704946041,"remaining_time":0.3969214627},
{"learn":[3.610713743],"iteration":660,"passed_time":0.771333704,"remaining_time":0.3955856666},
{"learn":[3.610044025],"iteration":661,"passed_time":0.7721384793,"remaining_time":0.3942338459},
{"learn":[3.607342669],"iteration":662,"passed_time":0.7729182108,"remaining_time":0.3928709458},
{"learn":[3.602510618],"iteration":663,"passed_time":0.7737248153,"remaining_time":0.3915234005},
{"learn":[3.600492392],"iteration":664,"passed_time":0.7744572142,"remaining_time":0.3901401004},
{"learn":[3.597171065],"iteration":665,"passed_time":0.7752282222,"remaining_time":0.3887781175},
{"learn":[3.594358798],"iteration":666,"passed_time":0.7759326315,"remaining_time":0.3873846571},
{"learn":[3.593945251],"iteration":667,"passed_time":0.7766006832,"remaining_time":0.3859751898},
{"learn":[3.593607748],"iteration":668,"passed_time":0.7773758455,"remaining_time":0.384620934},
{"learn":[3.592238714],"iteration":669,"passed_time":0.7781231184,"remaining_time":0.3832546702},
{"learn":[3.590144654],"iteration":670,"passed_time":0.7788434856,"remaining_time":0.3818770593},
{"learn":[3.587151536],"iteration":671,"passed_time":0.779542636,"remaining_time":0.3804910485},
{"learn":[3.586070865],"iteration":672,"passed_time":0.780303783,"remaining_time":0.3791372022},
{"learn":[3.585102746],"iteration":673,"passed_time":0.7816592347,"remaining_time":0.3780725675},
{"learn":[3.584362847],"iteration":674,"passed_time":0.7836917336,"remaining_time":0.3773330569},
{"learn":[3.581407561],"iteration":675,"passed_time":0.7851980918,"remaining_time":0.376337547},
{"learn":[3.57919422],"iteration":676,"passed_time":0.7862356508,"remaining_time":0.3751168614},
{"learn":[3.577632204],"iteration":677,"passed_time":0.7871334506,"remaining_time":0.3738303409},
{"learn":[3.573911195],"iteration":678,"passed_time":0.7879280428,"remaining_time":0.3724961734},
{"learn":[3.573408216],"iteration":679,"passed_time":0.7886673113,"remaining_time":0.3711375583},
{"learn":[3.571076482],"iteration":680,"passed_time":0.7894268989,"remaining_time":0.3697902801},
{"learn":[3.568177107],"iteration":681,"passed_time":0.7901866897,"remaining_time":0.3684448201},
{"learn":[3.564824621],"iteration":682,"passed_time":0.7909189165,"remaining_time":0.3670882819},
{"learn":[3.562475026],"iteration":683,"passed_time":0.7916984813,"remaining_time":0.3657554387},
{"learn":[3.561226889],"iteration":684,"passed_time":0.7924627601,"remaining_time":0.3644171816},
{"learn":[3.559383467],"iteration":685,"passed_time":0.7932508529,"remaining_time":0.3630914983},
{"learn":[3.555209766],"iteration":686,"passed_time":0.7940798044,"remaining_time":0.3617859953},
{"learn":[3.55345383],"iteration":687,"passed_time":0.7948365758,"remaining_time":0.3604491448},
{"learn":[3.552300968],"iteration":688,"passed_time":0.7983168639,"remaining_time":0.3603433159},
{"learn":[3.551253986],"iteration":689,"passed_time":0.8002371732,"remaining_time":0.3595268459},
{"learn":[3.549807725],"iteration":690,"passed_time":0.8011963884,"remaining_time":0.3582774009},
{"learn":[3.547992926],"iteration":691,"passed_time":0.802248383,"remaining_time":0.3570700895},
{"learn":[3.545438607],"iteration":692,"passed_time":0.8030763988,"remaining_time":0.3557640035},
{"learn":[3.543313763],"iteration":693,"passed_time":0.8039422947,"remaining_time":0.3544759974},
{"learn":[3.542962896],"iteration":694,"passed_time":0.80478953,"remaining_time":0.3531810168},
{"learn":[3.539800465],"iteration":695,"passed_time":0.8056200828,"remaining_time":0.3518800362},
{"learn":[3.53953187],"iteration":696,"passed_time":0.8064154663,"remaining_time":0.3505651166},
{"learn":[3.536332425],"iteration":697,"passed_time":0.8072157311,"remaining_time":0.3492537977},
{"learn":[3.534993327],"iteration":698,"passed_time":0.8080326379,"remaining_time":0.3479511073},
{"learn":[3.531637011],"iteration":699,"passed_time":0.8090641339,"remaining_time":0.3467417717},
{"learn":[3.531040284],"iteration":700,"passed_time":0.8100066513,"remaining_time":0.3454949911},
{"learn":[3.529973872],"iteration":701,"passed_time":0.8125307787,"remaining_time":0.344920473},
{"learn":[3.527325183],"iteration":702,"passed_time":0.8152381694,"remaining_time":0.3444178326},
{"learn":[3.527200815],"iteration":703,"passed_time":0.8164605405,"remaining_time":0.3432845454},
{"learn":[3.523459911],"iteration":704,"passed_time":0.8175074137,"remaining_time":0.3420775703},
{"learn":[3.522729934],"iteration":705,"passed_time":0.8185250309,"remaining_time":0.3408588655},
{"learn":[3.522260582],"iteration":706,"passed_time":0.819507204,"remaining_time":0.3396260407},
{"learn":[3.518641591],"iteration":707,"passed_time":0.8202223337,"remaining_time":0.3382837873},
{"learn":[3.516856405],"iteration":708,"passed_time":0.8210192636,"remaining_time":0.3369768769},
{"learn":[3.515083413],"iteration":709,"passed_time":0.8220289208,"remaining_time":0.3357582916},
{"learn":[3.514671214],"iteration":710,"passed_time":0.8230508887,"remaining_time":0.3345452979},
{"learn":[3.512617621],"iteration":711,"passed_time":0.8237605168,"remaining_time":0.3332065012},
{"learn":[3.510747971],"iteration":712,"passed_time":0.8243873816,"remaining_time":0.331836155},
{"learn":[3.508149266],"iteration":713,"passed_time":0.8250341067,"remaining_time":0.3304758467},
{"learn":[3.504557165],"iteration":714,"passed_time":0.8256781258,"remaining_time":0.3291164558},
{"learn":[3.501367208],"iteration":715,"passed_time":0.8268540504,"remaining_time":0.3279700424},
{"learn":[3.497593362],"iteration":716,"passed_time":0.8279588073,"remaining_time":0.3267954567},
{"learn":[3.496291169],"iteration":717,"passed_time":0.828896021,"remaining_time":0.3255552617},
{"learn":[3.49330374],"iteration":718,"passed_time":0.8296801153,"remaining_time":0.3242560673},
{"learn":[3.490044385],"iteration":719,"passed_time":0.830375362,"remaining_time":0.3229237519},
{"learn":[3.488891789],"iteration":720,"passed_time":0.8310277671,"remaining_time":0.3215766255},
{"learn":[3.486869081],"iteration":721,"passed_time":0.8316595921,"remaining_time":0.3202234995},
{"learn":[3.486303638],"iteration":722,"passed_time":0.8323699631,"remaining_time":0.3189024617},
{"learn":[3.486035862],"iteration":723,"passed_time":0.8330186357,"remaining_time":0.3175595904},
{"learn":[3.482668951],"iteration":724,"passed_time":0.8336871745,"remaining_time":0.3162261697},
{"learn":[3.47820549],"iteration":725,"passed_time":0.834356903,"remaining_time":0.3148950295},
{"learn":[3.474392283],"iteration":726,"passed_time":0.8350352053,"remaining_time":0.3135689285},
{"learn":[3.472268163],"iteration":727,"passed_time":0.835672322,"remaining_time":0.3122292192},
{"learn":[3.471209164],"iteration":728,"passed_time":0.8363073162,"remaining_time":0.3108906484},
{"learn":[3.470049971],"iteration":729,"passed_time":0.8370449297,"remaining_time":0.3095919603},
{"learn":[3.469078654],"iteration":730,"passed_time":0.837889498,"remaining_time":0.3083341655},
{"learn":[3.468643292],"iteration":731,"passed_time":0.8385645296,"remaining_time":0.3070154289},
{"learn":[3.468134848],"iteration":732,"passed_time":0.8392099728,"remaining_time":0.3056876709},
{"learn":[3.467820182],"iteration":733,"passed_time":0.839815749,"remaining_time":0.3043473968},
{"learn":[3.465776156],"iteration":734,"passed_time":0.8404428952,"remaining_time":0.3030168262},
{"learn":[3.463037608],"iteration":735,"passed_time":0.8412863769,"remaining_time":0.3017657656},
{"learn":[3.45965637],"iteration":736,"passed_time":0.8424164007,"remaining_time":0.3006180643},
{"learn":[3.457275091],"iteration":737,"passed_time":0.8436075228,"remaining_time":0.2994921016},
{"learn":[3.455522955],"iteration":738,"passed_time":0.8447549799,"remaining_time":0.2983505409},
{"learn":[3.451270508],"iteration":739,"passed_time":0.8456001333,"remaining_time":0.2971027495},
{"learn":[3.450978947],"iteration":740,"passed_time":0.8463950817,"remaining_time":0.2958384968},
{"learn":[3.450608492],"iteration":741,"passed_time":0.847343108,"remaining_time":0.2946287357},
{"learn":[3.448122004],"iteration":742,"passed_time":0.8480522643,"remaining_time":0.2933370551},
{"learn":[3.445646714],"iteration":743,"passed_time":0.8487147663,"remaining_time":0.2920308873},
{"learn":[3.44411263],"iteration":744,"passed_time":0.8493636561,"remaining_time":0.2907217883},
{"learn":[3.443264164],"iteration":745,"passed_time":0.8500104988,"remaining_time":0.2894137623},
{"learn":[3.439521363],"iteration":746,"passed_time":0.850634274,"remaining_time":0.2880996939},
{"learn":[3.436809225],"iteration":747,"passed_time":0.8512932674,"remaining_time":0.2867993361},
{"learn":[3.435509465],"iteration":748,"passed_time":0.8519404048,"remaining_time":0.2854967178},
{"learn":[3.434450277],"iteration":749,"passed_time":0.8525970183,"remaining_time":0.2841990061},
{"learn":[3.431786753],"iteration":750,"passed_time":0.8532519463,"remaining_time":0.2829024429},
{"learn":[3.430150302],"iteration":751,"passed_time":0.8538738349,"remaining_time":0.2815966902},
{"learn":[3.42696281],"iteration":752,"passed_time":0.8545452415,"remaining_time":0.2803089969},
{"learn":[3.426870334],"iteration":753,"passed_time":0.8551828415,"remaining_time":0.2790119085},
{"learn":[3.425200309],"iteration":754,"passed_time":0.8558340169,"remaining_time":0.2777209724},
{"learn":[3.423383783],"iteration":755,"passed_time":0.8569629149,"remaining_time":0.2765859143},
{"learn":[3.422752979],"iteration":756,"passed_time":0.8577892072,"remaining_time":0.2753537349},
{"learn":[3.420845924],"iteration":757,"passed_time":0.8586506241,"remaining_time":0.2741338404},
{"learn":[3.418917862],"iteration":758,"passed_time":0.859457025,"remaining_time":0.2728974216},
{"learn":[3.417095735],"iteration":759,"passed_time":0.8600717974,"remaining_time":0.2716016202},
{"learn":[3.414391848],"iteration":760,"passed_time":0.860662052,"remaining_time":0.2702999086},
{"learn":[3.41426711],"iteration":761,"passed_time":0.861244353,"remaining_time":0.2689975801},
{"learn":[3.411976013],"iteration":762,"passed_time":0.8618715213,"remaining_time":0.2677110754},
{"learn":[3.408614844],"iteration":763,"passed_time":0.8624670449,"remaining_time":0.2664165217},
{"learn":[3.407906721],"iteration":764,"passed_time":0.8630989241,"remaining_time":0.2651349636},
{"learn":[3.407494015],"iteration":765,"passed_time":0.8636998871,"remaining_time":0.2638456574},
{"learn":[3.406287128],"iteration":766,"passed_time":0.8643040219,"remaining_time":0.2625591096},
{"learn":[3.404600442],"iteration":767,"passed_time":0.8648942036,"remaining_time":0.261270124},
{"learn":[3.404012662],"iteration":768,"passed_time":0.8655079739,"remaining_time":0.2599900416},
{"learn":[3.400398762],"iteration":769,"passed_time":0.8661821426,"remaining_time":0.2587297309},
{"learn":[3.399737714],"iteration":770,"passed_time":0.8668124286,"remaining_time":0.2574579068},
{"learn":[3.399185251],"iteration":771,"passed_time":0.8674694403,"remaining_time":0.2561956378},
{"learn":[3.397245411],"iteration":772,"passed_time":0.8681106806,"remaining_time":0.2549303034},
{"learn":[3.396229831],"iteration":773,"passed_time":0.8687193272,"remaining_time":0.2536570645},
{"learn":[3.394002836],"iteration":774,"passed_time":0.8693648841,"remaining_time":0.2523962567},
{"learn":[3.389617243],"iteration":775,"passed_time":0.8700191759,"remaining_time":0.2511395559},
{"learn":[3.385426488],"iteration":776,"passed_time":0.8707235317,"remaining_time":0.2498987742},
{"learn":[3.385072258],"iteration":777,"passed_time":0.8717978442,"remaining_time":0.2487649375},
{"learn":[3.383842366],"iteration":778,"passed_time":0.8730307355,"remaining_time":0.247676242},
{"learn":[3.380110746],"iteration":779,"passed_time":0.8744700706,"remaining_time":0.2466454045},
{"learn":[3.378595218],"iteration":780,"passed_time":0.8754126094,"remaining_time":0.2454742144},
{"learn":[3.377371219],"iteration":781,"passed_time":0.876171019,"remaining_time":0.244252279},
{"learn":[3.375814782],"iteration":782,"passed_time":0.8769552564,"remaining_time":0.2430386854},
{"learn":[3.374195887],"iteration":783,"passed_time":0.8777632152,"remaining_time":0.2418327225},
{"learn":[3.373704309],"iteration":784,"passed_time":0.8789780784,"remaining_time":0.2407392189},
{"learn":[3.372971757],"iteration":785,"passed_time":0.8808553099,"remaining_time":0.239825746},
{"learn":[3.371565136],"iteration":786,"passed_time":0.8821235413,"remaining_time":0.2387449991},
{"learn":[3.3700309],"iteration":787,"passed_time":0.8831919737,"remaining_time":0.2376100234},
{"learn":[3.368186663],"iteration":788,"passed_time":0.8841435688,"remaining_time":0.2364439709},
{"learn":[3.366710398],"iteration":789,"passed_time":0.8850606181,"remaining_time":0.2352692782},
{"learn":[3.364598042],"iteration":790,"passed_time":0.8858593846,"remaining_time":0.234063984},
{"learn":[3.36348442],"iteration":791,"passed_time":0.8883370004,"remaining_time":0.2333006264},
{"learn":[3.362001759],"iteration":792,"passed_time":0.8897629384,"remaining_time":0.2322584215},
{"learn":[3.361580401],"iteration":793,"passed_time":0.8920439861,"remaining_time":0.2314371047},
{"learn":[3.359543675],"iteration":794,"passed_time":0.893739691,"remaining_time":0.2304611782},
{"learn":[3.35766119],"iteration":795,"passed_time":0.8945580524,"remaining_time":0.2292585963},
{"learn":[3.354592969],"iteration":796,"passed_time":0.8956443274,"remaining_time":0.2281252176},
{"learn":[3.350985986],"iteration":797,"passed_time":0.8966839555,"remaining_time":0.2269801491},
{"learn":[3.349589624],"iteration":798,"passed_time":0.8976043487,"remaining_time":0.2258053493},
{"learn":[3.349110856],"iteration":799,"passed_time":0.8985411169,"remaining_time":0.2246352792},
{"learn":[3.345315441],"iteration":800,"passed_time":0.8994364657,"remaining_time":0.2234555015},
{"learn":[3.34397474],"iteration":801,"passed_time":0.9005111598,"remaining_time":0.2223207103},
{"learn":[3.343800902],"iteration":802,"passed_time":0.9020719943,"remaining_time":0.2213053336},
{"learn":[3.342329465],"iteration":803,"passed_time":0.9036533106,"remaining_time":0.2202935931},
{"learn":[3.34220347],"iteration":804,"passed_time":0.9049564895,"remaining_time":0.2192130627},
{"learn":[3.341279219],"iteration":805,"passed_time":0.9058228322,"remaining_time":0.2180268355},
{"learn":[3.337329521],"iteration":806,"passed_time":0.9066460479,"remaining_time":0.216831087},
{"learn":[3.336708453],"iteration":807,"passed_time":0.9074073089,"remaining_time":0.2156215388},
{"learn":[3.333252703],"iteration":808,"passed_time":0.9085242368,"remaining_time":0.2144970695},
{"learn":[3.332186769],"iteration":809,"passed_time":0.9096555932,"remaining_time":0.2133760033},
{"learn":[3.330594851],"iteration":810,"passed_time":0.9105799071,"remaining_time":0.2122066615},
{"learn":[3.327867442],"iteration":811,"passed_time":0.9113726748,"remaining_time":0.2110074666},
{"learn":[3.327563111],"iteration":812,"passed_time":0.9121245691,"remaining_time":0.2097998701},
{"learn":[3.326308994],"iteration":813,"passed_time":0.9131542726,"remaining_time":0.2086568731},
{"learn":[3.326249879],"iteration":814,"passed_time":0.9138577499,"remaining_time":0.2074401027},
{"learn":[3.322336238],"iteration":815,"passed_time":0.9146625563,"remaining_time":0.2062474392},
{"learn":[3.320491154],"iteration":816,"passed_time":0.9155402803,"remaining_time":0.2050720579},
{"learn":[3.320434271],"iteration":817,"passed_time":0.9224542046,"remaining_time":0.205240422},
{"learn":[3.319609638],"iteration":818,"passed_time":0.9239111617,"remaining_time":0.2041854948},
{"learn":[3.316182682],"iteration":819,"passed_time":0.9247867181,"remaining_time":0.2030019625},
{"learn":[3.313126612],"iteration":820,"passed_time":0.9255957987,"remaining_time":0.2018046869},
{"learn":[3.311222803],"iteration":821,"passed_time":0.9263774356,"remaining_time":0.2006024131},
{"learn":[3.309627335],"iteration":822,"passed_time":0.9271797094,"remaining_time":0.1994055997},
{"learn":[3.307974895],"iteration":823,"passed_time":0.9281395341,"remaining_time":0.1982433956},
{"learn":[3.307321505],"iteration":824,"passed_time":0.9290843872,"remaining_time":0.1970785064},
{"learn":[3.306759087],"iteration":825,"passed_time":0.9298959823,"remaining_time":0.1958860786},
{"learn":[3.30484037],"iteration":826,"passed_time":0.9332812362,"remaining_time":0.1952329551},
{"learn":[3.30201994],"iteration":827,"passed_time":0.9360373169,"remaining_time":0.1944425344},
{"learn":[3.299302297],"iteration":828,"passed_time":0.9396125874,"remaining_time":0.1938163479},
{"learn":[3.298132671],"iteration":829,"passed_time":0.9407253945,"remaining_time":0.1926786953},
{"learn":[3.296976183],"iteration":830,"passed_time":0.941789021,"remaining_time":0.1915311005},
{"learn":[3.293144745],"iteration":831,"passed_time":0.9430345642,"remaining_time":0.1904204408},
{"learn":[3.290284404],"iteration":832,"passed_time":0.9439591219,"remaining_time":0.1892451061},
{"learn":[3.288285745],"iteration":833,"passed_time":0.9448070275,"remaining_time":0.1880551158},
{"learn":[3.286662667],"iteration":834,"passed_time":0.9456138325,"remaining_time":0.1868578232},
{"learn":[3.285692682],"iteration":835,"passed_time":0.9464245183,"remaining_time":0.1856622261},
{"learn":[3.284565611],"iteration":836,"passed_time":0.9472459139,"remaining_time":0.1844696344},
{"learn":[3.283897383],"iteration":837,"passed_time":0.9487528051,"remaining_time":0.1834104468},
{"learn":[3.280712855],"iteration":838,"passed_time":0.9499830218,"remaining_time":0.1822970995},
{"learn":[3.280468341],"iteration":839,"passed_time":0.9508775513,"remaining_time":0.1811195336},
{"learn":[3.277814895],"iteration":840,"passed_time":0.9519673302,"remaining_time":0.1799795547},
{"learn":[3.276316385],"iteration":841,"passed_time":0.9529843509,"remaining_time":0.1788260421},
{"learn":[3.27557063],"iteration":842,"passed_time":0.9538119638,"remaining_time":0.1776375781},
{"learn":[3.27499628],"iteration":843,"passed_time":0.9545365571,"remaining_time":0.1764309276},
{"learn":[3.273569958],"iteration":844,"passed_time":0.9552789046,"remaining_time":0.1752286748},
{"learn":[3.269665595],"iteration":845,"passed_time":0.9560882364,"remaining_time":0.1740397026},
{"learn":[3.267984685],"iteration":846,"passed_time":0.9569434152,"remaining_time":0.1728599085},
{"learn":[3.267702508],"iteration":847,"passed_time":0.9576723519,"remaining_time":0.1716582518},
{"learn":[3.266671924],"iteration":848,"passed_time":0.9584162712,"remaining_time":0.1704603733},
{"learn":[3.265359825],"iteration":849,"passed_time":0.9592304273,"remaining_time":0.1692759578},
{"learn":[3.2618983],"iteration":850,"passed_time":0.9603013822,"remaining_time":0.1681373748},
{"learn":[3.260456253],"iteration":851,"passed_time":0.9612541963,"remaining_time":0.1669784285},
{"learn":[3.258389147],"iteration":852,"passed_time":0.9622303543,"remaining_time":0.1658239884},
{"learn":[3.258108469],"iteration":853,"passed_time":0.9644331271,"remaining_time":0.1648796681},
{"learn":[3.256424936],"iteration":854,"passed_time":0.966566299,"remaining_time":0.1639206004},
{"learn":[3.254817983],"iteration":855,"passed_time":0.9678039855,"remaining_time":0.1628081471},
{"learn":[3.253898449],"iteration":856,"passed_time":0.9687262707,"remaining_time":0.1616427733},
{"learn":[3.253023652],"iteration":857,"passed_time":0.9695855135,"remaining_time":0.1604675325},
{"learn":[3.252845542],"iteration":858,"passed_time":0.9704431631,"remaining_time":0.159292766},
{"learn":[3.252316026],"iteration":859,"passed_time":0.9711875766,"remaining_time":0.1581003032},
{"learn":[3.24975301],"iteration":860,"passed_time":0.9718814887,"remaining_time":0.1569007281},
{"learn":[3.249151075],"iteration":861,"passed_time":0.9725233037,"remaining_time":0.155693986},
{"learn":[3.246257135],"iteration":862,"passed_time":0.9732067861,"remaining_time":0.1544951677},
{"learn":[3.243826471],"iteration":863,"passed_time":0.9738733127,"remaining_time":0.1532948733},
{"learn":[3.243190653],"iteration":864,"passed_time":0.9745194396,"remaining_time":0.1520926293},
{"learn":[3.24008797],"iteration":865,"passed_time":0.9751420593,"remaining_time":0.1508880323},
{"learn":[3.240036811],"iteration":866,"passed_time":0.9757349785,"remaining_time":0.1496802216},
{"learn":[3.238676314],"iteration":867,"passed_time":0.97638102,"remaining_time":0.1484819063},
{"learn":[3.237848782],"iteration":868,"passed_time":0.9771760409,"remaining_time":0.1473073203},
{"learn":[3.236405498],"iteration":869,"passed_time":0.9780942921,"remaining_time":0.1461520207},
{"learn":[3.233378068],"iteration":870,"passed_time":0.9791485696,"remaining_time":0.1450174116},
{"learn":[3.233169169],"iteration":871,"passed_time":0.9800406707,"remaining_time":0.143859181},
{"learn":[3.232434885],"iteration":872,"passed_time":0.9808325008,"remaining_time":0.1426869732},
{"learn":[3.229978115],"iteration":873,"passed_time":0.9815806939,"remaining_time":0.1415093449},
{"learn":[3.229648848],"iteration":874,"passed_time":0.9822476703,"remaining_time":0.1403210958},
{"learn":[3.227208761],"iteration":875,"passed_time":0.982929957,"remaining_time":0.139136204},
{"learn":[3.226258869],"iteration":876,"passed_time":0.9836488423,"remaining_time":0.1379575913},
{"learn":[3.225331995],"iteration":877,"passed_time":0.9843035922,"remaining_time":0.1367711142},
{"learn":[3.221968268],"iteration":878,"passed_time":0.9849562927,"remaining_time":0.1355855648},
{"learn":[3.221166317],"iteration":879,"passed_time":0.9855918704,"remaining_time":0.1343988914},
{"learn":[3.220047503],"iteration":880,"passed_time":0.9862438544,"remaining_time":0.1332156852},
{"learn":[3.21982781],"iteration":881,"passed_time":0.986864127,"remaining_time":0.132029441},
{"learn":[3.216693405],"iteration":882,"passed_time":0.9874973776,"remaining_time":0.1308461984},
{"learn":[3.214798761],"iteration":883,"passed_time":0.9881306756,"remaining_time":0.1296642063},
{"learn":[3.214395085],"iteration":884,"passed_time":0.9888579987,"remaining_time":0.1284956721},
{"learn":[3.213470696],"iteration":885,"passed_time":0.9895658254,"remaining_time":0.1273256254},
{"learn":[3.211595017],"iteration":886,"passed_time":0.9902905347,"remaining_time":0.1261587716},
{"learn":[3.210965255],"iteration":887,"passed_time":0.9909849677,"remaining_time":0.124989095},
{"learn":[3.209413583],"iteration":888,"passed_time":0.9916708099,"remaining_time":0.123819415},
{"learn":[3.208331683],"iteration":889,"passed_time":0.9923351196,"remaining_time":0.1226481609},
{"learn":[3.207110711],"iteration":890,"passed_time":0.9932481871,"remaining_time":0.1215084763},
{"learn":[3.204519413],"iteration":891,"passed_time":0.99420292,"remaining_time":0.1203743446},
{"learn":[3.201421296],"iteration":892,"passed_time":0.9951399445,"remaining_time":0.1192384928},
{"learn":[3.200691259],"iteration":893,"passed_time":0.9960439379,"remaining_time":0.1180991694},
{"learn":[3.200485067],"iteration":894,"passed_time":0.9967730761,"remaining_time":0.1169398581},
{"learn":[3.197467568],"iteration":895,"passed_time":0.9975352611,"remaining_time":0.1157853428},
{"learn":[3.195838544],"iteration":896,"passed_time":0.9981599252,"remaining_time":0.1146159111},
{"learn":[3.195671746],"iteration":897,"passed_time":0.9987775854,"remaining_time":0.1134468972},
{"learn":[3.194213094],"iteration":898,"passed_time":0.999431986,"remaining_time":0.1122832376},
{"learn":[3.192884691],"iteration":899,"passed_time":1.000091781,"remaining_time":0.111121309},
{"learn":[3.188364239],"iteration":900,"passed_time":1.000756274,"remaining_time":0.1099610113},
{"learn":[3.185219478],"iteration":901,"passed_time":1.001475862,"remaining_time":0.1088077988},
{"learn":[3.184120387],"iteration":902,"passed_time":1.002267913,"remaining_time":0.1076633306},
{"learn":[3.183725321],"iteration":903,"passed_time":1.003054852,"remaining_time":0.1065190993},
{"learn":[3.181264554],"iteration":904,"passed_time":1.003694612,"remaining_time":0.1053602079},
{"learn":[3.180741589],"iteration":905,"passed_time":1.004332321,"remaining_time":0.1042022496},
{"learn":[3.179782639],"iteration":906,"passed_time":1.004987329,"remaining_time":0.1030472124},
{"learn":[3.176377564],"iteration":907,"passed_time":1.005634163,"remaining_time":0.1018924482},
{"learn":[3.174078182],"iteration":908,"passed_time":1.006286983,"remaining_time":0.1007394009},
{"learn":[3.171242379],"iteration":909,"passed_time":1.006942382,"remaining_time":0.0995877081},
{"learn":[3.170421012],"iteration":910,"passed_time":1.007701254,"remaining_time":0.09844721365},
{"learn":[3.170087224],"iteration":911,"passed_time":1.008929029,"remaining_time":0.09735280105},
{"learn":[3.167303059],"iteration":912,"passed_time":1.010370302,"remaining_time":0.0962784406},
{"learn":[3.16705966],"iteration":913,"passed_time":1.011198006,"remaining_time":0.09514554546},
{"learn":[3.165667683],"iteration":914,"passed_time":1.01189781,"remaining_time":0.09400143593},
{"learn":[3.164689733],"iteration":915,"passed_time":1.012529467,"remaining_time":0.09285204719},
{"learn":[3.163311455],"iteration":916,"passed_time":1.013167741,"remaining_time":0.09170438655},
{"learn":[3.159425016],"iteration":917,"passed_time":1.013828648,"remaining_time":0.09055985744},
{"learn":[3.159327058],"iteration":918,"passed_time":1.014495125,"remaining_time":0.08941687171},
{"learn":[3.15819426],"iteration":919,"passed_time":1.01523528,"remaining_time":0.0882813287},
{"learn":[3.157086603],"iteration":920,"passed_time":1.015953637,"remaining_time":0.08714477452},
{"learn":[3.153354154],"iteration":921,"passed_time":1.016612834,"remaining_time":0.08600412264},
{"learn":[3.153261317],"iteration":922,"passed_time":1.017228036,"remaining_time":0.08486084371},
{"learn":[3.153168454],"iteration":923,"passed_time":1.017844552,"remaining_time":0.08371881599},
{"learn":[3.152080399],"iteration":924,"passed_time":1.018493468,"remaining_time":0.08258055142},
{"learn":[3.151635144],"iteration":925,"passed_time":1.019142575,"remaining_time":0.08144335909},
{"learn":[3.147762655],"iteration":926,"passed_time":1.019843305,"remaining_time":0.08031128505},
{"learn":[3.147172317],"iteration":927,"passed_time":1.020558037,"remaining_time":0.07918122699},
{"learn":[3.146254125],"iteration":928,"passed_time":1.021357754,"remaining_time":0.07805855813},
{"learn":[3.144869828],"iteration":929,"passed_time":1.022182857,"remaining_time":0.07693849461},
{"learn":[3.143466218],"iteration":930,"passed_time":1.023136561,"remaining_time":0.07582859584},
{"learn":[3.141919643],"iteration":931,"passed_time":1.024336028,"remaining_time":0.07473696343},
{"learn":[3.141054135],"iteration":932,"passed_time":1.025220838,"remaining_time":0.07362250388},
{"learn":[3.139390417],"iteration":933,"passed_time":1.026243432,"remaining_time":0.07251827248},
{"learn":[3.139025283],"iteration":934,"passed_time":1.026993763,"remaining_time":0.07139528833},
{"learn":[3.137824183],"iteration":935,"passed_time":1.02773223,"remaining_time":0.07027228923},
{"learn":[3.135620453],"iteration":936,"passed_time":1.028423135,"remaining_time":0.06914691305},
{"learn":[3.13443178],"iteration":937,"passed_time":1.029093796,"remaining_time":0.06802112512},
{"learn":[3.132765713],"iteration":938,"passed_time":1.029761677,"remaining_time":0.06689612596},
{"learn":[3.131434124],"iteration":939,"passed_time":1.030407184,"remaining_time":0.06577067133},
{"learn":[3.128384262],"iteration":940,"passed_time":1.031044584,"remaining_time":0.06464572845},
{"learn":[3.128120455],"iteration":941,"passed_time":1.031671422,"remaining_time":0.06352117034},
{"learn":[3.126314615],"iteration":942,"passed_time":1.032318418,"remaining_time":0.06239888636},
{"learn":[3.125409666],"iteration":943,"passed_time":1.032968532,"remaining_time":0.06127779429},
{"learn":[3.123072589],"iteration":944,"passed_time":1.033698277,"remaining_time":0.0601623336},
{"learn":[3.122921099],"iteration":945,"passed_time":1.034529829,"remaining_time":0.05905349973},
{"learn":[3.122182662],"iteration":946,"passed_time":1.035411861,"remaining_time":0.05794807671},
{"learn":[3.120040951],"iteration":947,"passed_time":1.036377124,"remaining_time":0.05684769033},
{"learn":[3.118767799],"iteration":948,"passed_time":1.037207377,"remaining_time":0.05574033323},
{"learn":[3.118203218],"iteration":949,"passed_time":1.03824153,"remaining_time":0.05464429103},
{"learn":[3.116343362],"iteration":950,"passed_time":1.039770402,"remaining_time":0.05357386931},
{"learn":[3.11480829],"iteration":951,"passed_time":1.041346128,"remaining_time":0.0525048468},
{"learn":[3.112607903],"iteration":952,"passed_time":1.042281484,"remaining_time":0.05140317917},
{"learn":[3.111661241],"iteration":953,"passed_time":1.043081113,"remaining_time":0.05029531573},
{"learn":[3.110249676],"iteration":954,"passed_time":1.043862524,"remaining_time":0.04918723936},
{"learn":[3.107333579],"iteration":955,"passed_time":1.044692232,"remaining_time":0.04808206927},
{"learn":[3.107149851],"iteration":956,"passed_time":1.045313428,"remaining_time":0.04696810594},
{"learn":[3.106867336],"iteration":957,"passed_time":1.045966342,"remaining_time":0.04585656196},
{"learn":[3.10364681],"iteration":958,"passed_time":1.046628663,"remaining_time":0.04474637664},
{"learn":[3.102703811],"iteration":959,"passed_time":1.047399073,"remaining_time":0.04364162804},
{"learn":[3.101469264],"iteration":960,"passed_time":1.048032475,"remaining_time":0.04253201513},
{"learn":[3.09863569],"iteration":961,"passed_time":1.048698795,"remaining_time":0.04142469254},
{"learn":[3.09645939],"iteration":962,"passed_time":1.049359472,"remaining_time":0.040318069},
{"learn":[3.096240186],"iteration":963,"passed_time":1.049954249,"remaining_time":0.03920990972},
{"learn":[3.094838828],"iteration":964,"passed_time":1.050609291,"remaining_time":0.03810500019},
{"learn":[3.094176802],"iteration":965,"passed_time":1.0512934,"remaining_time":0.03700204515},
{"learn":[3.093182279],"iteration":966,"passed_time":1.052263294,"remaining_time":0.03590970909},
{"learn":[3.090150687],"iteration":967,"passed_time":1.053319738,"remaining_time":0.0348204872},
{"learn":[3.088612829],"iteration":968,"passed_time":1.054751355,"remaining_time":0.03374333539},
{"learn":[3.087153684],"iteration":969,"passed_time":1.056155345,"remaining_time":0.0326645983},
{"learn":[3.085866843],"iteration":970,"passed_time":1.057031737,"remaining_time":0.03156943396},
{"learn":[3.082669094],"iteration":971,"passed_time":1.057761155,"remaining_time":0.03047048595},
{"learn":[3.081047548],"iteration":972,"passed_time":1.0583947,"remaining_time":0.02936963711},
{"learn":[3.079684322],"iteration":973,"passed_time":1.059067816,"remaining_time":0.02827080411},
{"learn":[3.07613431],"iteration":974,"passed_time":1.059834105,"remaining_time":0.02717523346},
{"learn":[3.074005935],"iteration":975,"passed_time":1.060575367,"remaining_time":0.02607972213},
{"learn":[3.072988853],"iteration":976,"passed_time":1.061195137,"remaining_time":0.02498207591},
{"learn":[3.072344268],"iteration":977,"passed_time":1.061795252,"remaining_time":0.02388496478},
{"learn":[3.070654438],"iteration":978,"passed_time":1.062400273,"remaining_time":0.02278897419},
{"learn":[3.069724506],"iteration":979,"passed_time":1.063011842,"remaining_time":0.02169411922},
{"learn":[3.067763166],"iteration":980,"passed_time":1.063620325,"remaining_time":0.02060018979},
{"learn":[3.066737893],"iteration":981,"passed_time":1.064300037,"remaining_time":0.01950855466},
{"learn":[3.065248174],"iteration":982,"passed_time":1.065032477,"remaining_time":0.01841866948},
{"learn":[3.063186837],"iteration":983,"passed_time":1.065876403,"remaining_time":0.01733132363},
{"learn":[3.062880371],"iteration":984,"passed_time":1.066699577,"remaining_time":0.01624415599},
{"learn":[3.061288645],"iteration":985,"passed_time":1.067494245,"remaining_time":0.0151571191},
{"learn":[3.059970575],"iteration":986,"passed_time":1.068362837,"remaining_time":0.01407164832},
{"learn":[3.059576341],"iteration":987,"passed_time":1.069557699,"remaining_time":0.01299057934},
{"learn":[3.058175919],"iteration":988,"passed_time":1.070718412,"remaining_time":0.01190890044},
{"learn":[3.056830702],"iteration":989,"passed_time":1.072950392,"remaining_time":0.01083788275},
{"learn":[3.056336579],"iteration":990,"passed_time":1.073799624,"remaining_time":0.009751964296},
{"learn":[3.055810414],"iteration":991,"passed_time":1.074530014,"remaining_time":0.00866556463},
{"learn":[3.055476518],"iteration":992,"passed_time":1.07529699,"remaining_time":0.007580139911},
{"learn":[3.053331734],"iteration":993,"passed_time":1.076207187,"remaining_time":0.006496220442},
{"learn":[3.050890374],"iteration":994,"passed_time":1.077823939,"remaining_time":0.005416200698},
{"learn":[3.04972623],"iteration":995,"passed_time":1.078830272,"remaining_time":0.004332651693},
{"learn":[3.047217327],"iteration":996,"passed_time":1.07951352,"remaining_time":0.003248285416},
{"learn":[3.047155483],"iteration":997,"passed_time":1.080171979,"remaining_time":0.002164673304},
{"learn":[3.04430671],"iteration":998,"passed_time":1.0807989,"remaining_time":0.001081880781},
{"learn":[3.042664195],"iteration":999,"passed_time":1.081461677,"remaining_time":0}
]}